{"title": "Intermezzo aus Cavalleria rusticana", "composer": null, "performer": null, "label": "253 Welte-Mignon", "type": "welte-red", "PURL": "https://purl.stanford.edu/vm351pv9656", "holeData": [{"x": 406, "y": 15688, "w": 27, "h": 50, "m": 21, "t": 11}, {"x": 3763, "y": 16035, "w": 27, "h": 62, "m": 110, "t": 100}, {"x": 255, "y": 16077, "w": 27, "h": 62, "m": 17, "t": 7}, {"x": 2522, "y": 16205, "w": 27, "h": 1964, "m": 77, "t": 67}, {"x": 2333, "y": 16207, "w": 27, "h": 1928, "m": 72, "t": 62}, {"x": 2221, "y": 16208, "w": 27, "h": 1798, "m": 69, "t": 59}, {"x": 2070, "y": 16209, "w": 27, "h": 1750, "m": 65, "t": 55}, {"x": 3613, "y": 16247, "w": 27, "h": 63, "m": 106, "t": 96}, {"x": 3801, "y": 16247, "w": 26, "h": 62, "m": 111, "t": 101}, {"x": 217, "y": 16278, "w": 27, "h": 62, "m": 16, "t": 6}, {"x": 3764, "y": 16764, "w": 27, "h": 62, "m": 110, "t": 100}, {"x": 255, "y": 16817, "w": 27, "h": 63, "m": 17, "t": 7}, {"x": 3651, "y": 16895, "w": 27, "h": 75, "m": 107, "t": 97}, {"x": 2673, "y": 17008, "w": 27, "h": 1148, "m": 81, "t": 71}, {"x": 2032, "y": 17010, "w": 27, "h": 878, "m": 64, "t": 54}, {"x": 3801, "y": 17014, "w": 27, "h": 74, "m": 111, "t": 101}, {"x": 217, "y": 17055, "w": 28, "h": 63, "m": 16, "t": 6}, {"x": 3613, "y": 17156, "w": 27, "h": 64, "m": 106, "t": 96}, {"x": 3765, "y": 17478, "w": 27, "h": 50, "m": 110, "t": 100}, {"x": 257, "y": 17520, "w": 27, "h": 49, "m": 17, "t": 7}, {"x": 3652, "y": 17630, "w": 27, "h": 62, "m": 107, "t": 97}, {"x": 1957, "y": 17757, "w": 27, "h": 203, "m": 62, "t": 52}, {"x": 2788, "y": 17810, "w": 26, "h": 346, "m": 84, "t": 74}, {"x": 3803, "y": 17841, "w": 27, "h": 62, "m": 111, "t": 101}, {"x": 3615, "y": 17853, "w": 27, "h": 62, "m": 106, "t": 96}, {"x": 218, "y": 17883, "w": 28, "h": 38, "m": 16, "t": 6}, {"x": 3766, "y": 18029, "w": 27, "h": 51, "m": 110, "t": 100}, {"x": 257, "y": 18240, "w": 28, "h": 63, "m": 17, "t": 7}, {"x": 1693, "y": 18387, "w": 27, "h": 1408, "m": 55, "t": 45}, {"x": 1959, "y": 18395, "w": 27, "h": 883, "m": 62, "t": 52}, {"x": 3653, "y": 18424, "w": 27, "h": 51, "m": 107, "t": 97}, {"x": 2073, "y": 18433, "w": 26, "h": 1764, "m": 65, "t": 55}, {"x": 219, "y": 18465, "w": 27, "h": 62, "m": 16, "t": 6}, {"x": 3803, "y": 18506, "w": 27, "h": 75, "m": 111, "t": 101}, {"x": 2789, "y": 18522, "w": 26, "h": 1067, "m": 84, "t": 74}, {"x": 2412, "y": 18524, "w": 27, "h": 1788, "m": 74, "t": 64}, {"x": 3616, "y": 18648, "w": 27, "h": 63, "m": 106, "t": 96}, {"x": 2715, "y": 19435, "w": 26, "h": 439, "m": 82, "t": 72}, {"x": 260, "y": 19492, "w": 28, "h": 84, "m": 17, "t": 7}, {"x": 3769, "y": 19617, "w": 27, "h": 63, "m": 110, "t": 100}, {"x": 3656, "y": 19678, "w": 27, "h": 51, "m": 107, "t": 97}, {"x": 1773, "y": 19757, "w": 26, "h": 358, "m": 57, "t": 47}, {"x": 223, "y": 19774, "w": 27, "h": 50, "m": 16, "t": 6}, {"x": 2678, "y": 19776, "w": 27, "h": 724, "m": 81, "t": 71}, {"x": 3807, "y": 19795, "w": 27, "h": 63, "m": 111, "t": 101}, {"x": 3770, "y": 19949, "w": 27, "h": 63, "m": 110, "t": 100}, {"x": 3619, "y": 19950, "w": 27, "h": 62, "m": 106, "t": 96}, {"x": 262, "y": 19999, "w": 27, "h": 62, "m": 17, "t": 7}, {"x": 1810, "y": 20060, "w": 26, "h": 173, "m": 58, "t": 48}, {"x": 2604, "y": 20107, "w": 27, "h": 393, "m": 79, "t": 69}, {"x": 3657, "y": 20293, "w": 28, "h": 63, "m": 107, "t": 97}, {"x": 1849, "y": 20336, "w": 27, "h": 392, "m": 59, "t": 49}, {"x": 1962, "y": 20347, "w": 28, "h": 403, "m": 62, "t": 52}, {"x": 2078, "y": 20382, "w": 26, "h": 2117, "m": 65, "t": 55}, {"x": 224, "y": 20424, "w": 27, "h": 62, "m": 16, "t": 6}, {"x": 2869, "y": 20450, "w": 26, "h": 406, "m": 86, "t": 76}, {"x": 2417, "y": 20451, "w": 26, "h": 525, "m": 74, "t": 64}, {"x": 3809, "y": 20458, "w": 27, "h": 75, "m": 111, "t": 101}, {"x": 3621, "y": 20530, "w": 27, "h": 63, "m": 106, "t": 96}, {"x": 2530, "y": 20876, "w": 27, "h": 348, "m": 77, "t": 67}, {"x": 3772, "y": 20909, "w": 26, "h": 63, "m": 110, "t": 100}, {"x": 3659, "y": 21040, "w": 27, "h": 51, "m": 107, "t": 97}, {"x": 1888, "y": 21104, "w": 27, "h": 755, "m": 60, "t": 50}, {"x": 2681, "y": 21161, "w": 26, "h": 1016, "m": 81, "t": 71}, {"x": 2341, "y": 21162, "w": 27, "h": 803, "m": 72, "t": 62}, {"x": 3809, "y": 21193, "w": 27, "h": 62, "m": 111, "t": 101}, {"x": 3621, "y": 21288, "w": 27, "h": 51, "m": 106, "t": 96}, {"x": 3660, "y": 21757, "w": 27, "h": 51, "m": 107, "t": 97}, {"x": 1852, "y": 21821, "w": 27, "h": 714, "m": 59, "t": 49}, {"x": 2419, "y": 21866, "w": 26, "h": 786, "m": 74, "t": 64}, {"x": 3623, "y": 22017, "w": 27, "h": 52, "m": 106, "t": 96}, {"x": 3774, "y": 22291, "w": 27, "h": 50, "m": 110, "t": 100}, {"x": 265, "y": 22309, "w": 27, "h": 51, "m": 17, "t": 7}, {"x": 3661, "y": 22434, "w": 27, "h": 51, "m": 107, "t": 97}, {"x": 1890, "y": 22508, "w": 27, "h": 400, "m": 60, "t": 50}, {"x": 2042, "y": 22508, "w": 27, "h": 1247, "m": 64, "t": 54}, {"x": 2157, "y": 22577, "w": 26, "h": 436, "m": 67, "t": 57}, {"x": 2608, "y": 22588, "w": 27, "h": 343, "m": 79, "t": 69}, {"x": 2495, "y": 22589, "w": 27, "h": 1285, "m": 76, "t": 66}, {"x": 3812, "y": 22600, "w": 27, "h": 62, "m": 111, "t": 101}, {"x": 227, "y": 22617, "w": 28, "h": 62, "m": 16, "t": 6}, {"x": 3624, "y": 22647, "w": 27, "h": 49, "m": 106, "t": 96}, {"x": 3775, "y": 22914, "w": 27, "h": 62, "m": 110, "t": 100}, {"x": 266, "y": 22919, "w": 28, "h": 74, "m": 17, "t": 7}, {"x": 3662, "y": 23174, "w": 27, "h": 52, "m": 107, "t": 97}, {"x": 1928, "y": 23236, "w": 27, "h": 484, "m": 61, "t": 51}, {"x": 2684, "y": 23246, "w": 26, "h": 1504, "m": 81, "t": 71}, {"x": 2232, "y": 23247, "w": 27, "h": 757, "m": 69, "t": 59}, {"x": 3812, "y": 23281, "w": 27, "h": 63, "m": 111, "t": 101}, {"x": 228, "y": 23285, "w": 27, "h": 63, "m": 16, "t": 6}, {"x": 3624, "y": 23514, "w": 27, "h": 50, "m": 106, "t": 96}, {"x": 266, "y": 23955, "w": 26, "h": 64, "m": 17, "t": 7}, {"x": 3775, "y": 24011, "w": 26, "h": 63, "m": 110, "t": 100}, {"x": 3662, "y": 24070, "w": 27, "h": 65, "m": 107, "t": 97}, {"x": 1966, "y": 24121, "w": 27, "h": 524, "m": 62, "t": 52}, {"x": 2232, "y": 24133, "w": 26, "h": 463, "m": 69, "t": 59}, {"x": 2420, "y": 24133, "w": 26, "h": 652, "m": 74, "t": 64}, {"x": 2081, "y": 24134, "w": 27, "h": 463, "m": 65, "t": 55}, {"x": 228, "y": 24135, "w": 27, "h": 49, "m": 16, "t": 6}, {"x": 3624, "y": 24285, "w": 27, "h": 51, "m": 106, "t": 96}, {"x": 2533, "y": 24439, "w": 27, "h": 369, "m": 77, "t": 67}, {"x": 3812, "y": 24451, "w": 27, "h": 63, "m": 111, "t": 101}, {"x": 2495, "y": 24723, "w": 27, "h": 324, "m": 76, "t": 66}, {"x": 266, "y": 24842, "w": 27, "h": 64, "m": 17, "t": 7}, {"x": 3774, "y": 24995, "w": 27, "h": 62, "m": 110, "t": 100}, {"x": 2420, "y": 25008, "w": 27, "h": 202, "m": 74, "t": 64}, {"x": 1702, "y": 25148, "w": 26, "h": 454, "m": 55, "t": 45}, {"x": 1966, "y": 25171, "w": 27, "h": 478, "m": 62, "t": 52}, {"x": 2081, "y": 25184, "w": 27, "h": 501, "m": 65, "t": 55}, {"x": 228, "y": 25207, "w": 27, "h": 51, "m": 16, "t": 6}, {"x": 3661, "y": 25219, "w": 27, "h": 62, "m": 107, "t": 97}, {"x": 2307, "y": 25254, "w": 26, "h": 454, "m": 71, "t": 61}, {"x": 3698, "y": 25301, "w": 27, "h": 27, "m": 108, "t": 98}, {"x": 2419, "y": 25348, "w": 27, "h": 636, "m": 74, "t": 64}, {"x": 2871, "y": 25360, "w": 27, "h": 600, "m": 86, "t": 76}, {"x": 3735, "y": 25371, "w": 28, "h": 27, "m": 109, "t": 99}, {"x": 3623, "y": 25406, "w": 27, "h": 51, "m": 106, "t": 96}, {"x": 3810, "y": 25621, "w": 27, "h": 63, "m": 111, "t": 101}, {"x": 2757, "y": 25908, "w": 27, "h": 302, "m": 83, "t": 73}, {"x": 265, "y": 25932, "w": 26, "h": 64, "m": 17, "t": 7}, {"x": 1889, "y": 26027, "w": 27, "h": 913, "m": 60, "t": 50}, {"x": 3660, "y": 26027, "w": 27, "h": 51, "m": 107, "t": 97}, {"x": 2080, "y": 26052, "w": 26, "h": 876, "m": 65, "t": 55}, {"x": 2155, "y": 26063, "w": 26, "h": 841, "m": 67, "t": 57}, {"x": 3697, "y": 26099, "w": 27, "h": 28, "m": 108, "t": 98}, {"x": 2342, "y": 26135, "w": 27, "h": 805, "m": 72, "t": 62}, {"x": 3810, "y": 26135, "w": 27, "h": 122, "m": 111, "t": 101}, {"x": 2795, "y": 26147, "w": 27, "h": 781, "m": 84, "t": 74}, {"x": 226, "y": 26195, "w": 27, "h": 63, "m": 16, "t": 6}, {"x": 3621, "y": 26478, "w": 27, "h": 39, "m": 106, "t": 96}, {"x": 262, "y": 27078, "w": 27, "h": 51, "m": 17, "t": 7}, {"x": 3770, "y": 27090, "w": 27, "h": 62, "m": 110, "t": 100}, {"x": 1697, "y": 27267, "w": 27, "h": 345, "m": 55, "t": 45}, {"x": 3657, "y": 27278, "w": 27, "h": 39, "m": 107, "t": 97}, {"x": 1961, "y": 27302, "w": 27, "h": 333, "m": 62, "t": 52}, {"x": 2076, "y": 27361, "w": 27, "h": 345, "m": 65, "t": 55}, {"x": 222, "y": 27384, "w": 28, "h": 75, "m": 16, "t": 6}, {"x": 2263, "y": 27419, "w": 27, "h": 538, "m": 70, "t": 60}, {"x": 2715, "y": 27443, "w": 27, "h": 502, "m": 82, "t": 72}, {"x": 3806, "y": 27454, "w": 28, "h": 50, "m": 111, "t": 101}, {"x": 3618, "y": 27466, "w": 27, "h": 62, "m": 106, "t": 96}, {"x": 3769, "y": 27762, "w": 27, "h": 76, "m": 110, "t": 100}, {"x": 2413, "y": 27882, "w": 27, "h": 264, "m": 74, "t": 64}, {"x": 259, "y": 27907, "w": 27, "h": 51, "m": 17, "t": 7}, {"x": 3655, "y": 27966, "w": 27, "h": 51, "m": 107, "t": 97}, {"x": 1883, "y": 28013, "w": 27, "h": 699, "m": 60, "t": 50}, {"x": 2262, "y": 28096, "w": 27, "h": 908, "m": 70, "t": 60}, {"x": 2035, "y": 28097, "w": 27, "h": 556, "m": 64, "t": 54}, {"x": 2676, "y": 28119, "w": 26, "h": 686, "m": 81, "t": 71}, {"x": 220, "y": 28120, "w": 27, "h": 64, "m": 16, "t": 6}, {"x": 3805, "y": 28131, "w": 26, "h": 63, "m": 111, "t": 101}, {"x": 3616, "y": 28261, "w": 27, "h": 52, "m": 106, "t": 96}, {"x": 3766, "y": 28602, "w": 27, "h": 50, "m": 110, "t": 100}, {"x": 2599, "y": 28742, "w": 27, "h": 181, "m": 79, "t": 69}, {"x": 3803, "y": 28754, "w": 27, "h": 74, "m": 111, "t": 101}, {"x": 257, "y": 28862, "w": 27, "h": 63, "m": 17, "t": 7}, {"x": 3765, "y": 29000, "w": 27, "h": 62, "m": 110, "t": 100}, {"x": 3652, "y": 29059, "w": 27, "h": 50, "m": 107, "t": 97}, {"x": 1692, "y": 29073, "w": 27, "h": 750, "m": 55, "t": 45}, {"x": 1956, "y": 29084, "w": 27, "h": 703, "m": 62, "t": 52}, {"x": 2071, "y": 29167, "w": 27, "h": 678, "m": 65, "t": 55}, {"x": 217, "y": 29191, "w": 27, "h": 63, "m": 16, "t": 6}, {"x": 2259, "y": 29236, "w": 26, "h": 693, "m": 70, "t": 60}, {"x": 3614, "y": 29246, "w": 27, "h": 51, "m": 106, "t": 96}, {"x": 2710, "y": 29247, "w": 27, "h": 144, "m": 82, "t": 72}, {"x": 3802, "y": 29258, "w": 27, "h": 62, "m": 111, "t": 101}, {"x": 2786, "y": 29365, "w": 27, "h": 133, "m": 84, "t": 74}, {"x": 3764, "y": 29482, "w": 27, "h": 62, "m": 110, "t": 100}, {"x": 2710, "y": 29483, "w": 26, "h": 99, "m": 82, "t": 72}, {"x": 3801, "y": 29672, "w": 26, "h": 62, "m": 111, "t": 101}, {"x": 2408, "y": 29675, "w": 27, "h": 428, "m": 74, "t": 64}, {"x": 3763, "y": 29826, "w": 27, "h": 64, "m": 110, "t": 100}, {"x": 253, "y": 29834, "w": 27, "h": 51, "m": 17, "t": 7}, {"x": 2521, "y": 29877, "w": 27, "h": 295, "m": 77, "t": 67}, {"x": 3649, "y": 29969, "w": 27, "h": 63, "m": 107, "t": 97}, {"x": 1878, "y": 29974, "w": 26, "h": 683, "m": 60, "t": 50}, {"x": 2030, "y": 30043, "w": 27, "h": 730, "m": 64, "t": 54}, {"x": 2257, "y": 30053, "w": 26, "h": 614, "m": 70, "t": 60}, {"x": 3799, "y": 30107, "w": 27, "h": 74, "m": 111, "t": 101}, {"x": 2671, "y": 30110, "w": 26, "h": 765, "m": 81, "t": 71}, {"x": 214, "y": 30129, "w": 27, "h": 63, "m": 16, "t": 6}, {"x": 3611, "y": 30225, "w": 27, "h": 51, "m": 106, "t": 96}, {"x": 1914, "y": 30607, "w": 27, "h": 168, "m": 61, "t": 51}, {"x": 3761, "y": 30613, "w": 27, "h": 50, "m": 110, "t": 100}, {"x": 251, "y": 30857, "w": 27, "h": 51, "m": 17, "t": 7}, {"x": 2594, "y": 30896, "w": 27, "h": 338, "m": 79, "t": 69}, {"x": 3722, "y": 30903, "w": 27, "h": 50, "m": 109, "t": 99}, {"x": 3647, "y": 30950, "w": 27, "h": 63, "m": 107, "t": 97}, {"x": 1951, "y": 31039, "w": 27, "h": 383, "m": 62, "t": 52}, {"x": 2066, "y": 31063, "w": 26, "h": 323, "m": 65, "t": 55}, {"x": 2216, "y": 31110, "w": 27, "h": 345, "m": 69, "t": 59}, {"x": 212, "y": 31117, "w": 27, "h": 50, "m": 16, "t": 6}, {"x": 3684, "y": 31150, "w": 27, "h": 50, "m": 108, "t": 98}, {"x": 3609, "y": 31162, "w": 27, "h": 50, "m": 106, "t": 96}, {"x": 2518, "y": 31189, "w": 27, "h": 430, "m": 77, "t": 67}, {"x": 3722, "y": 31209, "w": 27, "h": 27, "m": 109, "t": 99}, {"x": 250, "y": 31390, "w": 27, "h": 63, "m": 17, "t": 7}, {"x": 3684, "y": 31494, "w": 27, "h": 27, "m": 108, "t": 98}, {"x": 2856, "y": 31532, "w": 28, "h": 597, "m": 86, "t": 76}, {"x": 3722, "y": 31539, "w": 27, "h": 63, "m": 109, "t": 99}, {"x": 1686, "y": 31585, "w": 27, "h": 1033, "m": 55, "t": 45}, {"x": 2066, "y": 31620, "w": 26, "h": 1566, "m": 65, "t": 55}, {"x": 3647, "y": 31635, "w": 27, "h": 52, "m": 107, "t": 97}, {"x": 212, "y": 31652, "w": 27, "h": 64, "m": 16, "t": 6}, {"x": 2292, "y": 31714, "w": 26, "h": 877, "m": 71, "t": 61}, {"x": 2518, "y": 31808, "w": 26, "h": 910, "m": 77, "t": 67}, {"x": 3609, "y": 31863, "w": 27, "h": 62, "m": 106, "t": 96}, {"x": 3684, "y": 32039, "w": 27, "h": 51, "m": 108, "t": 98}, {"x": 2781, "y": 32090, "w": 28, "h": 429, "m": 84, "t": 74}, {"x": 3797, "y": 32097, "w": 26, "h": 51, "m": 111, "t": 101}, {"x": 2743, "y": 32409, "w": 27, "h": 596, "m": 83, "t": 73}, {"x": 249, "y": 32564, "w": 28, "h": 62, "m": 17, "t": 7}, {"x": 2668, "y": 32691, "w": 27, "h": 289, "m": 81, "t": 71}, {"x": 3647, "y": 32744, "w": 27, "h": 63, "m": 107, "t": 97}, {"x": 1762, "y": 32802, "w": 27, "h": 743, "m": 57, "t": 47}, {"x": 212, "y": 32821, "w": 27, "h": 51, "m": 16, "t": 6}, {"x": 2405, "y": 32931, "w": 27, "h": 336, "m": 74, "t": 64}, {"x": 3609, "y": 32948, "w": 27, "h": 64, "m": 106, "t": 96}, {"x": 2593, "y": 32954, "w": 27, "h": 158, "m": 79, "t": 69}, {"x": 251, "y": 33061, "w": 27, "h": 64, "m": 17, "t": 7}, {"x": 1838, "y": 33220, "w": 27, "h": 326, "m": 59, "t": 49}, {"x": 2519, "y": 33227, "w": 27, "h": 124, "m": 77, "t": 67}, {"x": 3761, "y": 33256, "w": 27, "h": 65, "m": 110, "t": 100}, {"x": 213, "y": 33264, "w": 27, "h": 63, "m": 16, "t": 6}, {"x": 3648, "y": 33365, "w": 27, "h": 64, "m": 107, "t": 97}, {"x": 1876, "y": 33506, "w": 27, "h": 147, "m": 60, "t": 50}, {"x": 2142, "y": 33528, "w": 27, "h": 299, "m": 67, "t": 57}, {"x": 2519, "y": 33538, "w": 27, "h": 217, "m": 77, "t": 67}, {"x": 2330, "y": 33539, "w": 27, "h": 288, "m": 72, "t": 62}, {"x": 3799, "y": 33557, "w": 27, "h": 45, "m": 111, "t": 101}, {"x": 3610, "y": 33568, "w": 28, "h": 64, "m": 106, "t": 96}, {"x": 3762, "y": 33733, "w": 27, "h": 52, "m": 110, "t": 100}, {"x": 2481, "y": 33752, "w": 27, "h": 192, "m": 76, "t": 66}, {"x": 252, "y": 33765, "w": 27, "h": 50, "m": 17, "t": 7}, {"x": 3652, "y": 33802, "w": 26, "h": 57, "m": 107, "t": 97}, {"x": 1500, "y": 33911, "w": 27, "h": 486, "m": 50, "t": 40}, {"x": 2595, "y": 33928, "w": 26, "h": 180, "m": 79, "t": 69}, {"x": 1877, "y": 33933, "w": 26, "h": 262, "m": 60, "t": 50}, {"x": 2067, "y": 33943, "w": 27, "h": 157, "m": 65, "t": 55}, {"x": 3803, "y": 33944, "w": 26, "h": 59, "m": 111, "t": 101}, {"x": 214, "y": 33966, "w": 27, "h": 50, "m": 16, "t": 6}, {"x": 3614, "y": 34008, "w": 26, "h": 52, "m": 106, "t": 96}, {"x": 2219, "y": 34166, "w": 27, "h": 404, "m": 69, "t": 59}, {"x": 252, "y": 34202, "w": 27, "h": 50, "m": 17, "t": 7}, {"x": 3767, "y": 34225, "w": 27, "h": 56, "m": 110, "t": 100}, {"x": 3651, "y": 34284, "w": 27, "h": 52, "m": 107, "t": 97}, {"x": 1689, "y": 34346, "w": 27, "h": 582, "m": 55, "t": 45}, {"x": 1840, "y": 34368, "w": 27, "h": 571, "m": 59, "t": 49}, {"x": 2295, "y": 34400, "w": 26, "h": 499, "m": 71, "t": 61}, {"x": 2069, "y": 34403, "w": 26, "h": 723, "m": 65, "t": 55}, {"x": 2482, "y": 34423, "w": 27, "h": 429, "m": 76, "t": 66}, {"x": 3803, "y": 34426, "w": 27, "h": 52, "m": 111, "t": 101}, {"x": 214, "y": 34449, "w": 28, "h": 50, "m": 16, "t": 6}, {"x": 3615, "y": 34717, "w": 26, "h": 58, "m": 106, "t": 96}, {"x": 3768, "y": 34942, "w": 27, "h": 62, "m": 110, "t": 100}, {"x": 2408, "y": 35108, "w": 27, "h": 314, "m": 74, "t": 64}, {"x": 3802, "y": 35115, "w": 27, "h": 57, "m": 111, "t": 101}, {"x": 253, "y": 35193, "w": 27, "h": 63, "m": 17, "t": 7}, {"x": 3651, "y": 35205, "w": 27, "h": 61, "m": 107, "t": 97}, {"x": 1879, "y": 35314, "w": 27, "h": 217, "m": 60, "t": 50}, {"x": 2145, "y": 35371, "w": 26, "h": 1407, "m": 67, "t": 57}, {"x": 2333, "y": 35371, "w": 26, "h": 1418, "m": 72, "t": 62}, {"x": 2031, "y": 35372, "w": 27, "h": 1358, "m": 64, "t": 54}, {"x": 215, "y": 35397, "w": 28, "h": 63, "m": 16, "t": 6}, {"x": 3617, "y": 35514, "w": 27, "h": 60, "m": 106, "t": 96}, {"x": 255, "y": 35918, "w": 27, "h": 50, "m": 17, "t": 7}, {"x": 785, "y": 36066, "w": 27, "h": 201, "m": 31, "t": 21}, {"x": 1240, "y": 36074, "w": 26, "h": 203, "m": 43, "t": 33}, {"x": 217, "y": 36081, "w": 27, "h": 39, "m": 16, "t": 6}, {"x": 407, "y": 36490, "w": 27, "h": 27, "m": 21, "t": 11}, {"x": 256, "y": 36586, "w": 28, "h": 62, "m": 17, "t": 7}, {"x": 522, "y": 36773, "w": 27, "h": 183, "m": 24, "t": 14}, {"x": 975, "y": 36783, "w": 27, "h": 182, "m": 36, "t": 26}, {"x": 219, "y": 36787, "w": 27, "h": 50, "m": 16, "t": 6}, {"x": 3768, "y": 37263, "w": 26, "h": 62, "m": 110, "t": 100}, {"x": 257, "y": 37299, "w": 27, "h": 38, "m": 17, "t": 7}, {"x": 3654, "y": 37322, "w": 27, "h": 64, "m": 107, "t": 97}, {"x": 1958, "y": 37426, "w": 27, "h": 452, "m": 62, "t": 52}, {"x": 1807, "y": 37428, "w": 26, "h": 426, "m": 58, "t": 48}, {"x": 3805, "y": 37460, "w": 26, "h": 62, "m": 111, "t": 101}, {"x": 2412, "y": 37469, "w": 27, "h": 275, "m": 74, "t": 64}, {"x": 2261, "y": 37470, "w": 27, "h": 262, "m": 70, "t": 60}, {"x": 219, "y": 37495, "w": 27, "h": 51, "m": 16, "t": 6}, {"x": 3617, "y": 37555, "w": 27, "h": 64, "m": 106, "t": 96}, {"x": 3769, "y": 37897, "w": 27, "h": 50, "m": 110, "t": 100}, {"x": 258, "y": 37943, "w": 27, "h": 63, "m": 17, "t": 7}, {"x": 3656, "y": 38050, "w": 27, "h": 51, "m": 107, "t": 97}, {"x": 2488, "y": 38081, "w": 27, "h": 344, "m": 76, "t": 66}, {"x": 2338, "y": 38082, "w": 26, "h": 344, "m": 72, "t": 62}, {"x": 1884, "y": 38085, "w": 26, "h": 594, "m": 60, "t": 50}, {"x": 3806, "y": 38085, "w": 27, "h": 51, "m": 111, "t": 101}, {"x": 1771, "y": 38086, "w": 26, "h": 594, "m": 57, "t": 47}, {"x": 220, "y": 38120, "w": 27, "h": 50, "m": 16, "t": 6}, {"x": 3618, "y": 38178, "w": 27, "h": 63, "m": 106, "t": 96}, {"x": 260, "y": 38496, "w": 27, "h": 38, "m": 17, "t": 7}, {"x": 3694, "y": 38569, "w": 27, "h": 28, "m": 108, "t": 98}, {"x": 2603, "y": 38576, "w": 27, "h": 110, "m": 79, "t": 69}, {"x": 3657, "y": 38582, "w": 27, "h": 51, "m": 107, "t": 97}, {"x": 1696, "y": 38619, "w": 27, "h": 641, "m": 55, "t": 45}, {"x": 2528, "y": 38624, "w": 27, "h": 358, "m": 77, "t": 67}, {"x": 2415, "y": 38626, "w": 27, "h": 321, "m": 74, "t": 64}, {"x": 1809, "y": 38630, "w": 27, "h": 629, "m": 58, "t": 48}, {"x": 3732, "y": 38640, "w": 27, "h": 28, "m": 109, "t": 99}, {"x": 222, "y": 38662, "w": 27, "h": 49, "m": 16, "t": 6}, {"x": 3619, "y": 38783, "w": 27, "h": 64, "m": 106, "t": 96}, {"x": 3771, "y": 38960, "w": 26, "h": 63, "m": 110, "t": 100}, {"x": 261, "y": 38980, "w": 26, "h": 62, "m": 17, "t": 7}, {"x": 1773, "y": 39232, "w": 27, "h": 1992, "m": 57, "t": 47}, {"x": 3658, "y": 39233, "w": 27, "h": 40, "m": 107, "t": 97}, {"x": 1886, "y": 39243, "w": 27, "h": 1827, "m": 60, "t": 50}, {"x": 2491, "y": 39251, "w": 26, "h": 1450, "m": 76, "t": 66}, {"x": 2340, "y": 39252, "w": 27, "h": 1770, "m": 72, "t": 62}, {"x": 223, "y": 39287, "w": 27, "h": 62, "m": 16, "t": 6}, {"x": 2793, "y": 39629, "w": 27, "h": 461, "m": 84, "t": 74}, {"x": 3809, "y": 39647, "w": 27, "h": 75, "m": 111, "t": 101}, {"x": 3622, "y": 39825, "w": 27, "h": 50, "m": 106, "t": 96}, {"x": 3774, "y": 40129, "w": 27, "h": 50, "m": 110, "t": 100}, {"x": 2757, "y": 40289, "w": 27, "h": 341, "m": 83, "t": 73}, {"x": 3811, "y": 40334, "w": 26, "h": 62, "m": 111, "t": 101}, {"x": 414, "y": 40420, "w": 28, "h": 28, "m": 21, "t": 11}, {"x": 2682, "y": 40614, "w": 27, "h": 336, "m": 81, "t": 71}, {"x": 2494, "y": 40948, "w": 27, "h": 380, "m": 76, "t": 66}, {"x": 3774, "y": 41036, "w": 27, "h": 63, "m": 110, "t": 100}, {"x": 264, "y": 41086, "w": 27, "h": 61, "m": 17, "t": 7}, {"x": 3661, "y": 41095, "w": 27, "h": 62, "m": 107, "t": 97}, {"x": 1813, "y": 41197, "w": 27, "h": 675, "m": 58, "t": 48}, {"x": 1965, "y": 41220, "w": 27, "h": 628, "m": 62, "t": 52}, {"x": 2268, "y": 41242, "w": 26, "h": 581, "m": 70, "t": 60}, {"x": 2419, "y": 41265, "w": 27, "h": 627, "m": 74, "t": 64}, {"x": 3811, "y": 41272, "w": 27, "h": 50, "m": 111, "t": 101}, {"x": 225, "y": 41285, "w": 27, "h": 74, "m": 16, "t": 6}, {"x": 3623, "y": 41366, "w": 27, "h": 52, "m": 106, "t": 96}, {"x": 3775, "y": 41613, "w": 26, "h": 51, "m": 110, "t": 100}, {"x": 264, "y": 41636, "w": 27, "h": 63, "m": 17, "t": 7}, {"x": 3662, "y": 41780, "w": 27, "h": 50, "m": 107, "t": 97}, {"x": 1776, "y": 41833, "w": 27, "h": 593, "m": 57, "t": 47}, {"x": 1889, "y": 41833, "w": 27, "h": 605, "m": 60, "t": 50}, {"x": 2494, "y": 41853, "w": 27, "h": 536, "m": 76, "t": 66}, {"x": 2343, "y": 41854, "w": 27, "h": 535, "m": 72, "t": 62}, {"x": 3812, "y": 41873, "w": 27, "h": 50, "m": 111, "t": 101}, {"x": 226, "y": 41896, "w": 27, "h": 51, "m": 16, "t": 6}, {"x": 3624, "y": 42026, "w": 27, "h": 64, "m": 106, "t": 96}, {"x": 264, "y": 42155, "w": 27, "h": 63, "m": 17, "t": 7}, {"x": 3661, "y": 42299, "w": 28, "h": 62, "m": 107, "t": 97}, {"x": 2607, "y": 42349, "w": 27, "h": 87, "m": 79, "t": 69}, {"x": 3699, "y": 42357, "w": 27, "h": 51, "m": 108, "t": 98}, {"x": 1701, "y": 42400, "w": 27, "h": 583, "m": 55, "t": 45}, {"x": 1814, "y": 42400, "w": 27, "h": 594, "m": 58, "t": 48}, {"x": 2532, "y": 42409, "w": 27, "h": 630, "m": 77, "t": 67}, {"x": 2419, "y": 42410, "w": 27, "h": 476, "m": 74, "t": 64}, {"x": 3737, "y": 42417, "w": 27, "h": 51, "m": 109, "t": 99}, {"x": 226, "y": 42440, "w": 27, "h": 50, "m": 16, "t": 6}, {"x": 3624, "y": 42596, "w": 27, "h": 52, "m": 106, "t": 96}, {"x": 265, "y": 42773, "w": 27, "h": 50, "m": 17, "t": 7}, {"x": 3775, "y": 42855, "w": 27, "h": 63, "m": 110, "t": 100}, {"x": 1889, "y": 42978, "w": 27, "h": 792, "m": 60, "t": 50}, {"x": 1776, "y": 42979, "w": 27, "h": 791, "m": 57, "t": 47}, {"x": 3662, "y": 42997, "w": 27, "h": 64, "m": 107, "t": 97}, {"x": 2344, "y": 43000, "w": 26, "h": 745, "m": 72, "t": 62}, {"x": 2494, "y": 43000, "w": 27, "h": 757, "m": 76, "t": 66}, {"x": 226, "y": 43019, "w": 27, "h": 51, "m": 16, "t": 6}, {"x": 2796, "y": 43365, "w": 27, "h": 239, "m": 84, "t": 74}, {"x": 3812, "y": 43375, "w": 26, "h": 74, "m": 111, "t": 101}, {"x": 3624, "y": 43468, "w": 27, "h": 51, "m": 106, "t": 96}, {"x": 3776, "y": 43857, "w": 27, "h": 62, "m": 110, "t": 100}, {"x": 2760, "y": 44036, "w": 26, "h": 158, "m": 83, "t": 73}, {"x": 3813, "y": 44105, "w": 27, "h": 51, "m": 111, "t": 101}, {"x": 2684, "y": 44345, "w": 27, "h": 135, "m": 81, "t": 71}, {"x": 265, "y": 44527, "w": 27, "h": 51, "m": 17, "t": 7}, {"x": 3775, "y": 44535, "w": 27, "h": 63, "m": 110, "t": 100}, {"x": 2495, "y": 44655, "w": 27, "h": 155, "m": 76, "t": 66}, {"x": 1701, "y": 44795, "w": 27, "h": 545, "m": 55, "t": 45}, {"x": 1890, "y": 44852, "w": 27, "h": 393, "m": 60, "t": 50}, {"x": 2042, "y": 44898, "w": 27, "h": 346, "m": 64, "t": 54}, {"x": 3662, "y": 44908, "w": 27, "h": 50, "m": 107, "t": 97}, {"x": 2494, "y": 44968, "w": 27, "h": 500, "m": 76, "t": 66}, {"x": 2344, "y": 44969, "w": 26, "h": 499, "m": 72, "t": 62}, {"x": 3813, "y": 44979, "w": 27, "h": 62, "m": 111, "t": 101}, {"x": 226, "y": 44984, "w": 27, "h": 63, "m": 16, "t": 6}, {"x": 3624, "y": 45096, "w": 27, "h": 64, "m": 106, "t": 96}, {"x": 3775, "y": 45215, "w": 28, "h": 63, "m": 110, "t": 100}, {"x": 2796, "y": 45546, "w": 27, "h": 273, "m": 84, "t": 74}, {"x": 3812, "y": 45568, "w": 27, "h": 62, "m": 111, "t": 101}, {"x": 264, "y": 45772, "w": 27, "h": 74, "m": 17, "t": 7}, {"x": 377, "y": 45795, "w": 27, "h": 51, "m": 20, "t": 10}, {"x": 3774, "y": 45922, "w": 27, "h": 63, "m": 110, "t": 100}, {"x": 1664, "y": 45924, "w": 26, "h": 289, "m": 54, "t": 44}, {"x": 1889, "y": 45983, "w": 27, "h": 278, "m": 60, "t": 50}, {"x": 2042, "y": 46054, "w": 27, "h": 264, "m": 64, "t": 54}, {"x": 226, "y": 46080, "w": 27, "h": 62, "m": 16, "t": 6}, {"x": 3812, "y": 46137, "w": 27, "h": 61, "m": 111, "t": 101}, {"x": 2494, "y": 46161, "w": 27, "h": 205, "m": 76, "t": 66}, {"x": 3775, "y": 46338, "w": 27, "h": 63, "m": 110, "t": 100}, {"x": 264, "y": 46389, "w": 27, "h": 74, "m": 17, "t": 7}, {"x": 1626, "y": 46592, "w": 26, "h": 367, "m": 53, "t": 43}, {"x": 1889, "y": 46626, "w": 27, "h": 381, "m": 60, "t": 50}, {"x": 3661, "y": 46647, "w": 27, "h": 50, "m": 107, "t": 97}, {"x": 2494, "y": 46742, "w": 27, "h": 335, "m": 76, "t": 66}, {"x": 2230, "y": 46743, "w": 27, "h": 263, "m": 69, "t": 59}, {"x": 225, "y": 46755, "w": 27, "h": 62, "m": 16, "t": 6}, {"x": 3811, "y": 46776, "w": 27, "h": 73, "m": 111, "t": 101}, {"x": 3623, "y": 46846, "w": 27, "h": 64, "m": 106, "t": 96}, {"x": 263, "y": 46957, "w": 27, "h": 63, "m": 17, "t": 7}, {"x": 2418, "y": 47085, "w": 27, "h": 227, "m": 74, "t": 64}, {"x": 1624, "y": 47122, "w": 27, "h": 333, "m": 53, "t": 43}, {"x": 1851, "y": 47168, "w": 26, "h": 309, "m": 59, "t": 49}, {"x": 1964, "y": 47226, "w": 27, "h": 298, "m": 62, "t": 52}, {"x": 3774, "y": 47248, "w": 26, "h": 62, "m": 110, "t": 100}, {"x": 2154, "y": 47250, "w": 27, "h": 307, "m": 67, "t": 57}, {"x": 224, "y": 47263, "w": 27, "h": 63, "m": 16, "t": 6}, {"x": 3698, "y": 47377, "w": 27, "h": 27, "m": 108, "t": 98}, {"x": 3810, "y": 47424, "w": 27, "h": 63, "m": 111, "t": 101}, {"x": 2757, "y": 47425, "w": 27, "h": 314, "m": 83, "t": 73}, {"x": 262, "y": 47715, "w": 27, "h": 63, "m": 17, "t": 7}, {"x": 2682, "y": 47759, "w": 26, "h": 362, "m": 81, "t": 71}, {"x": 3774, "y": 47888, "w": 27, "h": 52, "m": 110, "t": 100}, {"x": 1586, "y": 47952, "w": 27, "h": 348, "m": 52, "t": 42}, {"x": 3660, "y": 48008, "w": 27, "h": 51, "m": 107, "t": 97}, {"x": 1888, "y": 48021, "w": 26, "h": 350, "m": 60, "t": 50}, {"x": 2153, "y": 48093, "w": 27, "h": 254, "m": 67, "t": 57}, {"x": 2605, "y": 48105, "w": 27, "h": 336, "m": 79, "t": 69}, {"x": 3814, "y": 48113, "w": 26, "h": 62, "m": 111, "t": 101}, {"x": 223, "y": 48119, "w": 27, "h": 63, "m": 16, "t": 6}, {"x": 3622, "y": 48199, "w": 27, "h": 63, "m": 106, "t": 96}, {"x": 2340, "y": 48451, "w": 27, "h": 249, "m": 72, "t": 62}, {"x": 261, "y": 48511, "w": 27, "h": 52, "m": 17, "t": 7}, {"x": 3772, "y": 48530, "w": 26, "h": 63, "m": 110, "t": 100}, {"x": 1509, "y": 48641, "w": 27, "h": 356, "m": 50, "t": 40}, {"x": 1773, "y": 48663, "w": 27, "h": 344, "m": 57, "t": 47}, {"x": 1886, "y": 48686, "w": 27, "h": 356, "m": 60, "t": 50}, {"x": 3658, "y": 48706, "w": 27, "h": 49, "m": 107, "t": 97}, {"x": 2529, "y": 48789, "w": 27, "h": 322, "m": 77, "t": 67}, {"x": 3812, "y": 48789, "w": 27, "h": 60, "m": 111, "t": 101}, {"x": 2076, "y": 48791, "w": 27, "h": 299, "m": 65, "t": 55}, {"x": 222, "y": 48806, "w": 27, "h": 52, "m": 16, "t": 6}, {"x": 3620, "y": 48846, "w": 28, "h": 63, "m": 106, "t": 96}, {"x": 411, "y": 49042, "w": 27, "h": 86, "m": 21, "t": 11}, {"x": 2227, "y": 49131, "w": 27, "h": 324, "m": 69, "t": 59}, {"x": 3771, "y": 49223, "w": 26, "h": 63, "m": 110, "t": 100}, {"x": 259, "y": 49231, "w": 27, "h": 63, "m": 17, "t": 7}, {"x": 1243, "y": 49312, "w": 27, "h": 393, "m": 43, "t": 33}, {"x": 3659, "y": 49365, "w": 26, "h": 49, "m": 107, "t": 97}, {"x": 1847, "y": 49393, "w": 27, "h": 334, "m": 59, "t": 49}, {"x": 2075, "y": 49441, "w": 27, "h": 332, "m": 65, "t": 55}, {"x": 2301, "y": 49463, "w": 27, "h": 332, "m": 71, "t": 61}, {"x": 2489, "y": 49463, "w": 27, "h": 380, "m": 76, "t": 66}, {"x": 221, "y": 49480, "w": 27, "h": 62, "m": 16, "t": 6}, {"x": 3807, "y": 49483, "w": 27, "h": 59, "m": 111, "t": 101}, {"x": 3619, "y": 49542, "w": 27, "h": 63, "m": 106, "t": 96}, {"x": 3769, "y": 50393, "w": 26, "h": 63, "m": 110, "t": 100}, {"x": 2413, "y": 50575, "w": 26, "h": 414, "m": 74, "t": 64}, {"x": 257, "y": 50699, "w": 27, "h": 62, "m": 17, "t": 7}, {"x": 3805, "y": 50746, "w": 27, "h": 63, "m": 111, "t": 101}, {"x": 3655, "y": 50770, "w": 27, "h": 63, "m": 107, "t": 97}, {"x": 1693, "y": 50824, "w": 27, "h": 344, "m": 55, "t": 45}, {"x": 1430, "y": 50825, "w": 27, "h": 355, "m": 48, "t": 38}, {"x": 1882, "y": 50870, "w": 27, "h": 297, "m": 60, "t": 50}, {"x": 2034, "y": 50929, "w": 27, "h": 1428, "m": 64, "t": 54}, {"x": 218, "y": 50947, "w": 27, "h": 62, "m": 16, "t": 6}, {"x": 2336, "y": 50951, "w": 27, "h": 1619, "m": 72, "t": 62}, {"x": 3616, "y": 51063, "w": 28, "h": 62, "m": 106, "t": 96}, {"x": 1240, "y": 51591, "w": 27, "h": 183, "m": 43, "t": 33}, {"x": 785, "y": 51593, "w": 27, "h": 183, "m": 31, "t": 21}, {"x": 520, "y": 52314, "w": 28, "h": 430, "m": 24, "t": 14}, {"x": 974, "y": 52323, "w": 27, "h": 419, "m": 36, "t": 26}, {"x": 368, "y": 52564, "w": 27, "h": 51, "m": 20, "t": 10}, {"x": 3765, "y": 52818, "w": 27, "h": 62, "m": 110, "t": 100}, {"x": 179, "y": 52825, "w": 27, "h": 63, "m": 15, "t": 5}, {"x": 3652, "y": 52983, "w": 27, "h": 62, "m": 107, "t": 97}, {"x": 329, "y": 53106, "w": 27, "h": 27, "m": 19, "t": 9}, {"x": 254, "y": 53118, "w": 27, "h": 27, "m": 17, "t": 7}, {"x": 1162, "y": 53137, "w": 28, "h": 205, "m": 41, "t": 31}, {"x": 292, "y": 53165, "w": 27, "h": 51, "m": 18, "t": 8}, {"x": 3689, "y": 53172, "w": 28, "h": 27, "m": 108, "t": 98}, {"x": 3614, "y": 53184, "w": 28, "h": 64, "m": 106, "t": 96}, {"x": 2673, "y": 53225, "w": 27, "h": 699, "m": 81, "t": 71}, {"x": 2221, "y": 53227, "w": 27, "h": 676, "m": 69, "t": 59}, {"x": 3802, "y": 53232, "w": 27, "h": 61, "m": 111, "t": 101}, {"x": 1766, "y": 53548, "w": 27, "h": 122, "m": 57, "t": 47}, {"x": 1428, "y": 53550, "w": 26, "h": 87, "m": 48, "t": 38}, {"x": 1616, "y": 53550, "w": 26, "h": 99, "m": 53, "t": 43}, {"x": 215, "y": 53568, "w": 27, "h": 64, "m": 16, "t": 6}, {"x": 253, "y": 53803, "w": 27, "h": 64, "m": 17, "t": 7}, {"x": 1616, "y": 53809, "w": 26, "h": 75, "m": 53, "t": 43}, {"x": 1766, "y": 53820, "w": 27, "h": 75, "m": 57, "t": 47}, {"x": 1879, "y": 53843, "w": 27, "h": 51, "m": 60, "t": 50}, {"x": 3765, "y": 53963, "w": 27, "h": 63, "m": 110, "t": 100}, {"x": 215, "y": 54041, "w": 27, "h": 63, "m": 16, "t": 6}, {"x": 1766, "y": 54116, "w": 27, "h": 74, "m": 57, "t": 47}, {"x": 2070, "y": 54126, "w": 27, "h": 75, "m": 65, "t": 55}, {"x": 1879, "y": 54127, "w": 27, "h": 62, "m": 60, "t": 50}, {"x": 3652, "y": 54380, "w": 27, "h": 62, "m": 107, "t": 97}, {"x": 254, "y": 54385, "w": 27, "h": 28, "m": 17, "t": 7}, {"x": 330, "y": 54385, "w": 26, "h": 28, "m": 19, "t": 9}, {"x": 1125, "y": 54416, "w": 27, "h": 239, "m": 40, "t": 30}, {"x": 2786, "y": 54432, "w": 27, "h": 226, "m": 84, "t": 74}, {"x": 2333, "y": 54434, "w": 27, "h": 226, "m": 72, "t": 62}, {"x": 292, "y": 54445, "w": 27, "h": 39, "m": 18, "t": 8}, {"x": 3802, "y": 54450, "w": 27, "h": 63, "m": 111, "t": 101}, {"x": 3614, "y": 54532, "w": 27, "h": 52, "m": 106, "t": 96}, {"x": 1427, "y": 54744, "w": 27, "h": 85, "m": 48, "t": 38}, {"x": 1879, "y": 54753, "w": 27, "h": 74, "m": 60, "t": 50}, {"x": 1690, "y": 54754, "w": 27, "h": 74, "m": 55, "t": 45}, {"x": 3764, "y": 54789, "w": 28, "h": 52, "m": 110, "t": 100}, {"x": 3652, "y": 55016, "w": 27, "h": 64, "m": 107, "t": 97}, {"x": 253, "y": 55023, "w": 27, "h": 39, "m": 17, "t": 7}, {"x": 329, "y": 55023, "w": 27, "h": 38, "m": 19, "t": 9}, {"x": 2522, "y": 55058, "w": 26, "h": 727, "m": 77, "t": 67}, {"x": 2069, "y": 55062, "w": 27, "h": 714, "m": 65, "t": 55}, {"x": 1046, "y": 55068, "w": 27, "h": 242, "m": 38, "t": 28}, {"x": 3801, "y": 55089, "w": 27, "h": 62, "m": 111, "t": 101}, {"x": 291, "y": 55097, "w": 27, "h": 62, "m": 18, "t": 8}, {"x": 3614, "y": 55197, "w": 27, "h": 64, "m": 106, "t": 96}, {"x": 1615, "y": 55364, "w": 27, "h": 122, "m": 53, "t": 43}, {"x": 1502, "y": 55375, "w": 27, "h": 111, "m": 50, "t": 40}, {"x": 1313, "y": 55388, "w": 27, "h": 99, "m": 45, "t": 35}, {"x": 215, "y": 55393, "w": 27, "h": 64, "m": 16, "t": 6}, {"x": 1503, "y": 55622, "w": 26, "h": 87, "m": 50, "t": 40}, {"x": 1616, "y": 55623, "w": 26, "h": 87, "m": 53, "t": 43}, {"x": 253, "y": 55629, "w": 27, "h": 76, "m": 17, "t": 7}, {"x": 1766, "y": 55633, "w": 27, "h": 99, "m": 57, "t": 47}, {"x": 3765, "y": 55752, "w": 27, "h": 52, "m": 110, "t": 100}, {"x": 1615, "y": 55906, "w": 28, "h": 63, "m": 53, "t": 43}, {"x": 215, "y": 55912, "w": 27, "h": 64, "m": 16, "t": 6}, {"x": 1766, "y": 55917, "w": 27, "h": 63, "m": 57, "t": 47}, {"x": 1955, "y": 55928, "w": 27, "h": 51, "m": 62, "t": 52}, {"x": 3651, "y": 56156, "w": 27, "h": 51, "m": 107, "t": 97}, {"x": 253, "y": 56160, "w": 28, "h": 27, "m": 17, "t": 7}, {"x": 329, "y": 56160, "w": 27, "h": 27, "m": 19, "t": 9}, {"x": 972, "y": 56192, "w": 28, "h": 242, "m": 36, "t": 26}, {"x": 292, "y": 56208, "w": 27, "h": 63, "m": 18, "t": 8}, {"x": 2673, "y": 56208, "w": 27, "h": 228, "m": 81, "t": 71}, {"x": 2221, "y": 56210, "w": 27, "h": 228, "m": 69, "t": 59}, {"x": 3802, "y": 56226, "w": 27, "h": 50, "m": 111, "t": 101}, {"x": 3614, "y": 56333, "w": 27, "h": 50, "m": 106, "t": 96}, {"x": 215, "y": 56492, "w": 27, "h": 63, "m": 16, "t": 6}, {"x": 3765, "y": 56497, "w": 27, "h": 63, "m": 110, "t": 100}, {"x": 1766, "y": 56509, "w": 27, "h": 74, "m": 57, "t": 47}, {"x": 1578, "y": 56510, "w": 26, "h": 75, "m": 52, "t": 42}, {"x": 1313, "y": 56511, "w": 27, "h": 75, "m": 45, "t": 35}, {"x": 3652, "y": 56745, "w": 27, "h": 39, "m": 107, "t": 97}, {"x": 254, "y": 56776, "w": 27, "h": 27, "m": 17, "t": 7}, {"x": 329, "y": 56788, "w": 27, "h": 28, "m": 19, "t": 9}, {"x": 2409, "y": 56800, "w": 27, "h": 263, "m": 74, "t": 64}, {"x": 3803, "y": 56804, "w": 26, "h": 62, "m": 111, "t": 101}, {"x": 897, "y": 56809, "w": 27, "h": 226, "m": 34, "t": 24}, {"x": 1955, "y": 56814, "w": 27, "h": 240, "m": 62, "t": 52}, {"x": 292, "y": 56836, "w": 27, "h": 39, "m": 18, "t": 8}, {"x": 3614, "y": 56899, "w": 28, "h": 63, "m": 106, "t": 96}, {"x": 3766, "y": 56957, "w": 26, "h": 62, "m": 110, "t": 100}, {"x": 1162, "y": 57113, "w": 27, "h": 99, "m": 41, "t": 31}, {"x": 1502, "y": 57123, "w": 27, "h": 99, "m": 50, "t": 40}, {"x": 1351, "y": 57124, "w": 27, "h": 98, "m": 46, "t": 36}, {"x": 215, "y": 57142, "w": 28, "h": 63, "m": 16, "t": 6}, {"x": 1351, "y": 57349, "w": 27, "h": 86, "m": 46, "t": 36}, {"x": 253, "y": 57367, "w": 27, "h": 63, "m": 17, "t": 7}, {"x": 1502, "y": 57372, "w": 27, "h": 75, "m": 50, "t": 40}, {"x": 1615, "y": 57384, "w": 27, "h": 74, "m": 53, "t": 43}, {"x": 3802, "y": 57419, "w": 26, "h": 62, "m": 111, "t": 101}, {"x": 2861, "y": 57424, "w": 26, "h": 155, "m": 86, "t": 76}, {"x": 2409, "y": 57426, "w": 27, "h": 167, "m": 74, "t": 64}, {"x": 1802, "y": 57625, "w": 26, "h": 79, "m": 58, "t": 48}, {"x": 215, "y": 57626, "w": 27, "h": 63, "m": 16, "t": 6}, {"x": 1502, "y": 57631, "w": 27, "h": 75, "m": 50, "t": 40}, {"x": 1615, "y": 57631, "w": 27, "h": 74, "m": 53, "t": 43}, {"x": 3765, "y": 57735, "w": 27, "h": 64, "m": 110, "t": 100}, {"x": 2787, "y": 57741, "w": 26, "h": 182, "m": 84, "t": 74}, {"x": 2333, "y": 57743, "w": 27, "h": 171, "m": 72, "t": 62}, {"x": 253, "y": 57922, "w": 27, "h": 39, "m": 17, "t": 7}, {"x": 329, "y": 57933, "w": 27, "h": 28, "m": 19, "t": 9}, {"x": 783, "y": 57954, "w": 27, "h": 264, "m": 31, "t": 21}, {"x": 291, "y": 57969, "w": 27, "h": 63, "m": 18, "t": 8}, {"x": 3652, "y": 57998, "w": 27, "h": 51, "m": 107, "t": 97}, {"x": 2711, "y": 58051, "w": 26, "h": 262, "m": 82, "t": 72}, {"x": 2259, "y": 58053, "w": 26, "h": 263, "m": 70, "t": 60}, {"x": 3802, "y": 58056, "w": 27, "h": 63, "m": 111, "t": 101}, {"x": 3614, "y": 58152, "w": 28, "h": 50, "m": 106, "t": 96}, {"x": 216, "y": 58171, "w": 27, "h": 62, "m": 16, "t": 6}, {"x": 3766, "y": 58327, "w": 26, "h": 63, "m": 110, "t": 100}, {"x": 1804, "y": 58339, "w": 27, "h": 145, "m": 58, "t": 48}, {"x": 1503, "y": 58341, "w": 27, "h": 133, "m": 50, "t": 40}, {"x": 1616, "y": 58341, "w": 27, "h": 144, "m": 53, "t": 43}, {"x": 1352, "y": 58342, "w": 26, "h": 144, "m": 46, "t": 36}, {"x": 254, "y": 58395, "w": 27, "h": 27, "m": 17, "t": 7}, {"x": 329, "y": 58395, "w": 27, "h": 38, "m": 19, "t": 9}, {"x": 2523, "y": 58405, "w": 27, "h": 133, "m": 77, "t": 67}, {"x": 2070, "y": 58409, "w": 27, "h": 132, "m": 65, "t": 55}, {"x": 292, "y": 58442, "w": 27, "h": 50, "m": 18, "t": 8}, {"x": 329, "y": 58666, "w": 27, "h": 38, "m": 19, "t": 9}, {"x": 972, "y": 58697, "w": 27, "h": 276, "m": 36, "t": 26}, {"x": 3652, "y": 58705, "w": 28, "h": 63, "m": 107, "t": 97}, {"x": 292, "y": 58736, "w": 27, "h": 75, "m": 18, "t": 8}, {"x": 2673, "y": 58758, "w": 27, "h": 781, "m": 81, "t": 71}, {"x": 2221, "y": 58761, "w": 27, "h": 791, "m": 69, "t": 59}, {"x": 3803, "y": 58776, "w": 27, "h": 61, "m": 111, "t": 101}, {"x": 3615, "y": 58870, "w": 27, "h": 63, "m": 106, "t": 96}, {"x": 215, "y": 58914, "w": 28, "h": 86, "m": 16, "t": 6}, {"x": 1428, "y": 59049, "w": 26, "h": 99, "m": 48, "t": 38}, {"x": 1125, "y": 59051, "w": 27, "h": 98, "m": 40, "t": 30}, {"x": 1352, "y": 59062, "w": 26, "h": 86, "m": 46, "t": 36}, {"x": 216, "y": 59068, "w": 27, "h": 63, "m": 16, "t": 6}, {"x": 254, "y": 59282, "w": 28, "h": 50, "m": 17, "t": 7}, {"x": 1428, "y": 59286, "w": 27, "h": 98, "m": 48, "t": 38}, {"x": 1352, "y": 59287, "w": 27, "h": 97, "m": 46, "t": 36}, {"x": 1579, "y": 59297, "w": 26, "h": 99, "m": 52, "t": 42}, {"x": 216, "y": 59505, "w": 27, "h": 60, "m": 16, "t": 6}, {"x": 3767, "y": 59550, "w": 27, "h": 63, "m": 110, "t": 100}, {"x": 1805, "y": 59585, "w": 27, "h": 109, "m": 58, "t": 48}, {"x": 1579, "y": 59586, "w": 27, "h": 109, "m": 52, "t": 42}, {"x": 1429, "y": 59587, "w": 27, "h": 109, "m": 48, "t": 38}, {"x": 3653, "y": 59848, "w": 27, "h": 51, "m": 107, "t": 97}, {"x": 255, "y": 59878, "w": 27, "h": 39, "m": 17, "t": 7}, {"x": 330, "y": 59878, "w": 27, "h": 39, "m": 19, "t": 9}, {"x": 2599, "y": 59889, "w": 26, "h": 500, "m": 79, "t": 69}, {"x": 3803, "y": 59895, "w": 27, "h": 63, "m": 111, "t": 101}, {"x": 2147, "y": 59903, "w": 26, "h": 500, "m": 67, "t": 57}, {"x": 974, "y": 59909, "w": 27, "h": 193, "m": 36, "t": 26}, {"x": 293, "y": 59914, "w": 27, "h": 63, "m": 18, "t": 8}, {"x": 3616, "y": 60003, "w": 26, "h": 62, "m": 106, "t": 96}, {"x": 3766, "y": 60096, "w": 27, "h": 51, "m": 110, "t": 100}, {"x": 216, "y": 60152, "w": 28, "h": 50, "m": 16, "t": 6}, {"x": 1805, "y": 60155, "w": 27, "h": 87, "m": 58, "t": 48}, {"x": 1579, "y": 60156, "w": 27, "h": 87, "m": 52, "t": 42}, {"x": 1429, "y": 60157, "w": 26, "h": 74, "m": 48, "t": 38}, {"x": 3653, "y": 60274, "w": 27, "h": 63, "m": 107, "t": 97}, {"x": 1805, "y": 60415, "w": 27, "h": 86, "m": 58, "t": 48}, {"x": 331, "y": 60446, "w": 26, "h": 39, "m": 19, "t": 9}, {"x": 3804, "y": 60450, "w": 26, "h": 62, "m": 111, "t": 101}, {"x": 3615, "y": 60451, "w": 28, "h": 62, "m": 106, "t": 96}, {"x": 255, "y": 60458, "w": 27, "h": 27, "m": 17, "t": 7}, {"x": 2260, "y": 60458, "w": 26, "h": 677, "m": 70, "t": 60}, {"x": 2712, "y": 60467, "w": 27, "h": 677, "m": 82, "t": 72}, {"x": 784, "y": 60479, "w": 27, "h": 218, "m": 31, "t": 21}, {"x": 293, "y": 60506, "w": 27, "h": 51, "m": 18, "t": 8}, {"x": 1353, "y": 60736, "w": 27, "h": 98, "m": 46, "t": 36}, {"x": 1240, "y": 60737, "w": 26, "h": 97, "m": 43, "t": 33}, {"x": 1504, "y": 60747, "w": 27, "h": 86, "m": 50, "t": 40}, {"x": 217, "y": 60773, "w": 29, "h": 55, "m": 16, "t": 6}, {"x": 255, "y": 60943, "w": 27, "h": 63, "m": 17, "t": 7}, {"x": 1692, "y": 60971, "w": 27, "h": 96, "m": 55, "t": 45}, {"x": 1353, "y": 60973, "w": 27, "h": 83, "m": 46, "t": 36}, {"x": 1504, "y": 60984, "w": 27, "h": 84, "m": 50, "t": 40}, {"x": 217, "y": 61142, "w": 27, "h": 75, "m": 16, "t": 6}, {"x": 3767, "y": 61147, "w": 27, "h": 51, "m": 110, "t": 100}, {"x": 1692, "y": 61242, "w": 27, "h": 84, "m": 55, "t": 45}, {"x": 1805, "y": 61242, "w": 27, "h": 84, "m": 58, "t": 48}, {"x": 1504, "y": 61255, "w": 27, "h": 61, "m": 50, "t": 40}, {"x": 3655, "y": 61466, "w": 27, "h": 50, "m": 107, "t": 97}, {"x": 255, "y": 61496, "w": 28, "h": 38, "m": 17, "t": 7}, {"x": 331, "y": 61507, "w": 27, "h": 38, "m": 19, "t": 9}, {"x": 2412, "y": 61518, "w": 27, "h": 265, "m": 74, "t": 64}, {"x": 1957, "y": 61521, "w": 27, "h": 265, "m": 62, "t": 52}, {"x": 899, "y": 61527, "w": 26, "h": 229, "m": 34, "t": 24}, {"x": 293, "y": 61554, "w": 28, "h": 39, "m": 18, "t": 8}, {"x": 3617, "y": 61619, "w": 27, "h": 63, "m": 106, "t": 96}, {"x": 218, "y": 61768, "w": 27, "h": 75, "m": 16, "t": 6}, {"x": 1505, "y": 61773, "w": 27, "h": 100, "m": 50, "t": 40}, {"x": 1618, "y": 61773, "w": 27, "h": 100, "m": 53, "t": 43}, {"x": 3805, "y": 61915, "w": 27, "h": 63, "m": 111, "t": 101}, {"x": 3654, "y": 61987, "w": 27, "h": 63, "m": 107, "t": 97}, {"x": 332, "y": 61993, "w": 27, "h": 27, "m": 19, "t": 9}, {"x": 256, "y": 62004, "w": 28, "h": 38, "m": 17, "t": 7}, {"x": 1164, "y": 62035, "w": 28, "h": 169, "m": 41, "t": 31}, {"x": 2676, "y": 62040, "w": 26, "h": 310, "m": 81, "t": 71}, {"x": 2224, "y": 62041, "w": 26, "h": 311, "m": 69, "t": 59}, {"x": 294, "y": 62051, "w": 27, "h": 64, "m": 18, "t": 8}, {"x": 3767, "y": 62058, "w": 27, "h": 50, "m": 110, "t": 100}, {"x": 3616, "y": 62164, "w": 27, "h": 63, "m": 106, "t": 96}, {"x": 1430, "y": 62282, "w": 27, "h": 110, "m": 48, "t": 38}, {"x": 1618, "y": 62282, "w": 27, "h": 122, "m": 53, "t": 43}, {"x": 1316, "y": 62295, "w": 27, "h": 98, "m": 45, "t": 35}, {"x": 218, "y": 62312, "w": 27, "h": 50, "m": 16, "t": 6}, {"x": 3805, "y": 62366, "w": 26, "h": 63, "m": 111, "t": 101}, {"x": 1769, "y": 62485, "w": 26, "h": 100, "m": 57, "t": 47}, {"x": 1430, "y": 62487, "w": 27, "h": 87, "m": 48, "t": 38}, {"x": 1618, "y": 62487, "w": 27, "h": 74, "m": 53, "t": 43}, {"x": 2789, "y": 62564, "w": 27, "h": 181, "m": 84, "t": 74}, {"x": 2336, "y": 62567, "w": 27, "h": 180, "m": 72, "t": 62}, {"x": 256, "y": 62741, "w": 27, "h": 51, "m": 17, "t": 7}, {"x": 1618, "y": 62783, "w": 27, "h": 87, "m": 53, "t": 43}, {"x": 1769, "y": 62793, "w": 27, "h": 75, "m": 57, "t": 47}, {"x": 1882, "y": 62805, "w": 27, "h": 51, "m": 60, "t": 50}, {"x": 3768, "y": 62843, "w": 27, "h": 50, "m": 110, "t": 100}, {"x": 332, "y": 63037, "w": 27, "h": 40, "m": 19, "t": 9}, {"x": 1050, "y": 63053, "w": 28, "h": 185, "m": 38, "t": 28}, {"x": 3656, "y": 63058, "w": 27, "h": 51, "m": 107, "t": 97}, {"x": 2526, "y": 63098, "w": 26, "h": 262, "m": 77, "t": 67}, {"x": 2073, "y": 63101, "w": 27, "h": 261, "m": 65, "t": 55}, {"x": 295, "y": 63120, "w": 27, "h": 62, "m": 18, "t": 8}, {"x": 3618, "y": 63199, "w": 27, "h": 63, "m": 106, "t": 96}, {"x": 1770, "y": 63314, "w": 27, "h": 72, "m": 57, "t": 47}, {"x": 1620, "y": 63315, "w": 26, "h": 73, "m": 53, "t": 43}, {"x": 219, "y": 63332, "w": 27, "h": 49, "m": 16, "t": 6}, {"x": 3657, "y": 63575, "w": 27, "h": 62, "m": 107, "t": 97}, {"x": 333, "y": 63599, "w": 27, "h": 28, "m": 19, "t": 9}, {"x": 258, "y": 63600, "w": 27, "h": 27, "m": 17, "t": 7}, {"x": 977, "y": 63620, "w": 27, "h": 158, "m": 36, "t": 26}, {"x": 296, "y": 63635, "w": 27, "h": 28, "m": 18, "t": 8}, {"x": 2678, "y": 63637, "w": 27, "h": 703, "m": 81, "t": 71}, {"x": 2226, "y": 63639, "w": 27, "h": 750, "m": 69, "t": 59}, {"x": 3807, "y": 63646, "w": 27, "h": 74, "m": 111, "t": 101}, {"x": 3619, "y": 63740, "w": 27, "h": 52, "m": 106, "t": 96}, {"x": 1319, "y": 63928, "w": 27, "h": 123, "m": 45, "t": 35}, {"x": 1621, "y": 63928, "w": 27, "h": 146, "m": 53, "t": 43}, {"x": 221, "y": 63932, "w": 27, "h": 51, "m": 16, "t": 6}, {"x": 1433, "y": 63940, "w": 27, "h": 134, "m": 48, "t": 38}, {"x": 1433, "y": 64177, "w": 27, "h": 77, "m": 48, "t": 38}, {"x": 1621, "y": 64178, "w": 27, "h": 97, "m": 53, "t": 43}, {"x": 1772, "y": 64188, "w": 26, "h": 98, "m": 57, "t": 47}, {"x": 3771, "y": 64440, "w": 27, "h": 62, "m": 110, "t": 100}, {"x": 1885, "y": 64458, "w": 27, "h": 75, "m": 60, "t": 50}, {"x": 1621, "y": 64460, "w": 27, "h": 74, "m": 53, "t": 43}, {"x": 1772, "y": 64471, "w": 27, "h": 62, "m": 57, "t": 47}, {"x": 3658, "y": 64699, "w": 26, "h": 51, "m": 107, "t": 97}, {"x": 259, "y": 64724, "w": 27, "h": 27, "m": 17, "t": 7}, {"x": 334, "y": 64724, "w": 27, "h": 28, "m": 19, "t": 9}, {"x": 978, "y": 64734, "w": 27, "h": 241, "m": 36, "t": 26}, {"x": 2603, "y": 64762, "w": 27, "h": 475, "m": 79, "t": 69}, {"x": 2151, "y": 64763, "w": 26, "h": 475, "m": 67, "t": 57}, {"x": 297, "y": 64773, "w": 27, "h": 26, "m": 18, "t": 8}, {"x": 3808, "y": 64782, "w": 26, "h": 51, "m": 111, "t": 101}, {"x": 3620, "y": 64877, "w": 27, "h": 52, "m": 106, "t": 96}, {"x": 1357, "y": 65016, "w": 26, "h": 227, "m": 46, "t": 36}, {"x": 1433, "y": 65028, "w": 26, "h": 214, "m": 48, "t": 38}, {"x": 1583, "y": 65028, "w": 27, "h": 237, "m": 52, "t": 42}, {"x": 3771, "y": 65042, "w": 27, "h": 62, "m": 110, "t": 100}, {"x": 3658, "y": 65124, "w": 27, "h": 39, "m": 107, "t": 97}, {"x": 334, "y": 65256, "w": 27, "h": 39, "m": 19, "t": 9}, {"x": 2528, "y": 65282, "w": 27, "h": 1172, "m": 77, "t": 67}, {"x": 2076, "y": 65284, "w": 27, "h": 1138, "m": 65, "t": 55}, {"x": 3620, "y": 65289, "w": 27, "h": 62, "m": 106, "t": 96}, {"x": 3808, "y": 65300, "w": 27, "h": 62, "m": 111, "t": 101}, {"x": 1167, "y": 65311, "w": 27, "h": 110, "m": 41, "t": 31}, {"x": 297, "y": 65327, "w": 27, "h": 38, "m": 18, "t": 8}, {"x": 1434, "y": 65533, "w": 27, "h": 133, "m": 48, "t": 38}, {"x": 1622, "y": 65533, "w": 27, "h": 134, "m": 53, "t": 43}, {"x": 1320, "y": 65534, "w": 27, "h": 121, "m": 45, "t": 35}, {"x": 221, "y": 65538, "w": 27, "h": 49, "m": 16, "t": 6}, {"x": 1435, "y": 65733, "w": 26, "h": 63, "m": 48, "t": 38}, {"x": 1623, "y": 65733, "w": 27, "h": 75, "m": 53, "t": 43}, {"x": 1773, "y": 65744, "w": 27, "h": 85, "m": 57, "t": 47}, {"x": 260, "y": 65951, "w": 27, "h": 50, "m": 17, "t": 7}, {"x": 1886, "y": 65993, "w": 27, "h": 86, "m": 60, "t": 50}, {"x": 1773, "y": 66006, "w": 27, "h": 74, "m": 57, "t": 47}, {"x": 1623, "y": 66007, "w": 27, "h": 74, "m": 53, "t": 43}, {"x": 3772, "y": 66117, "w": 27, "h": 63, "m": 110, "t": 100}, {"x": 336, "y": 66211, "w": 27, "h": 39, "m": 19, "t": 9}, {"x": 865, "y": 66257, "w": 27, "h": 158, "m": 33, "t": 23}, {"x": 298, "y": 66271, "w": 27, "h": 50, "m": 18, "t": 8}, {"x": 1435, "y": 66539, "w": 26, "h": 75, "m": 48, "t": 38}, {"x": 1887, "y": 66549, "w": 26, "h": 75, "m": 60, "t": 50}, {"x": 1774, "y": 66550, "w": 26, "h": 63, "m": 57, "t": 47}, {"x": 222, "y": 66555, "w": 27, "h": 63, "m": 16, "t": 6}, {"x": 1623, "y": 66563, "w": 27, "h": 51, "m": 53, "t": 43}, {"x": 3660, "y": 66708, "w": 27, "h": 52, "m": 107, "t": 97}, {"x": 261, "y": 66780, "w": 27, "h": 38, "m": 17, "t": 7}, {"x": 337, "y": 66780, "w": 27, "h": 38, "m": 19, "t": 9}, {"x": 3697, "y": 66780, "w": 27, "h": 63, "m": 108, "t": 98}, {"x": 905, "y": 66836, "w": 26, "h": 165, "m": 34, "t": 24}, {"x": 300, "y": 66850, "w": 27, "h": 39, "m": 18, "t": 8}, {"x": 3622, "y": 66862, "w": 27, "h": 63, "m": 106, "t": 96}, {"x": 3810, "y": 66862, "w": 27, "h": 61, "m": 111, "t": 101}, {"x": 2870, "y": 66865, "w": 27, "h": 400, "m": 86, "t": 76}, {"x": 2417, "y": 66867, "w": 27, "h": 400, "m": 74, "t": 64}, {"x": 1511, "y": 67101, "w": 27, "h": 74, "m": 50, "t": 40}, {"x": 1170, "y": 67102, "w": 27, "h": 74, "m": 41, "t": 31}, {"x": 1360, "y": 67102, "w": 26, "h": 73, "m": 46, "t": 36}, {"x": 224, "y": 67105, "w": 27, "h": 50, "m": 16, "t": 6}, {"x": 3774, "y": 67200, "w": 27, "h": 51, "m": 110, "t": 100}, {"x": 1360, "y": 67301, "w": 27, "h": 87, "m": 46, "t": 36}, {"x": 1511, "y": 67301, "w": 28, "h": 99, "m": 50, "t": 40}, {"x": 1625, "y": 67302, "w": 26, "h": 98, "m": 53, "t": 43}, {"x": 2871, "y": 67403, "w": 27, "h": 192, "m": 86, "t": 76}, {"x": 2419, "y": 67405, "w": 26, "h": 191, "m": 74, "t": 64}, {"x": 3812, "y": 67413, "w": 27, "h": 62, "m": 111, "t": 101}, {"x": 1512, "y": 67548, "w": 27, "h": 100, "m": 50, "t": 40}, {"x": 1625, "y": 67560, "w": 27, "h": 122, "m": 53, "t": 43}, {"x": 1814, "y": 67598, "w": 27, "h": 83, "m": 58, "t": 48}, {"x": 263, "y": 67670, "w": 27, "h": 62, "m": 17, "t": 7}, {"x": 2343, "y": 67711, "w": 26, "h": 301, "m": 72, "t": 62}, {"x": 2796, "y": 67722, "w": 27, "h": 323, "m": 84, "t": 74}, {"x": 3775, "y": 67849, "w": 27, "h": 63, "m": 110, "t": 100}, {"x": 339, "y": 67883, "w": 27, "h": 27, "m": 19, "t": 9}, {"x": 3662, "y": 67909, "w": 27, "h": 52, "m": 107, "t": 97}, {"x": 793, "y": 67929, "w": 27, "h": 170, "m": 31, "t": 21}, {"x": 302, "y": 67943, "w": 27, "h": 27, "m": 18, "t": 8}, {"x": 2720, "y": 68018, "w": 27, "h": 181, "m": 82, "t": 72}, {"x": 2268, "y": 68019, "w": 27, "h": 181, "m": 70, "t": 60}, {"x": 3812, "y": 68027, "w": 27, "h": 63, "m": 111, "t": 101}, {"x": 3624, "y": 68076, "w": 27, "h": 52, "m": 106, "t": 96}, {"x": 225, "y": 68155, "w": 27, "h": 50, "m": 16, "t": 6}, {"x": 3775, "y": 68205, "w": 27, "h": 74, "m": 110, "t": 100}, {"x": 1814, "y": 68281, "w": 26, "h": 64, "m": 58, "t": 48}, {"x": 1513, "y": 68282, "w": 26, "h": 75, "m": 50, "t": 40}, {"x": 1625, "y": 68283, "w": 27, "h": 75, "m": 53, "t": 43}, {"x": 2533, "y": 68315, "w": 26, "h": 289, "m": 77, "t": 67}, {"x": 2080, "y": 68316, "w": 27, "h": 276, "m": 65, "t": 55}, {"x": 3662, "y": 68466, "w": 27, "h": 52, "m": 107, "t": 97}, {"x": 264, "y": 68534, "w": 27, "h": 51, "m": 17, "t": 7}, {"x": 339, "y": 68546, "w": 27, "h": 27, "m": 19, "t": 9}, {"x": 982, "y": 68568, "w": 28, "h": 169, "m": 36, "t": 26}, {"x": 302, "y": 68594, "w": 27, "h": 39, "m": 18, "t": 8}, {"x": 3813, "y": 68621, "w": 26, "h": 62, "m": 111, "t": 101}, {"x": 2683, "y": 68624, "w": 27, "h": 815, "m": 81, "t": 71}, {"x": 2231, "y": 68625, "w": 27, "h": 814, "m": 69, "t": 59}, {"x": 3625, "y": 68633, "w": 27, "h": 50, "m": 106, "t": 96}, {"x": 1438, "y": 68873, "w": 26, "h": 98, "m": 48, "t": 38}, {"x": 1135, "y": 68874, "w": 27, "h": 97, "m": 40, "t": 30}, {"x": 1362, "y": 68874, "w": 27, "h": 98, "m": 46, "t": 36}, {"x": 226, "y": 68876, "w": 27, "h": 62, "m": 16, "t": 6}, {"x": 1439, "y": 69086, "w": 27, "h": 86, "m": 48, "t": 38}, {"x": 1363, "y": 69087, "w": 26, "h": 85, "m": 46, "t": 36}, {"x": 1589, "y": 69098, "w": 27, "h": 85, "m": 52, "t": 42}, {"x": 265, "y": 69264, "w": 27, "h": 63, "m": 17, "t": 7}, {"x": 3777, "y": 69281, "w": 27, "h": 63, "m": 110, "t": 100}, {"x": 1816, "y": 69390, "w": 26, "h": 87, "m": 58, "t": 48}, {"x": 1439, "y": 69391, "w": 27, "h": 86, "m": 48, "t": 38}, {"x": 1590, "y": 69391, "w": 27, "h": 87, "m": 52, "t": 42}, {"x": 3664, "y": 69623, "w": 27, "h": 64, "m": 107, "t": 97}, {"x": 341, "y": 69628, "w": 27, "h": 28, "m": 19, "t": 9}, {"x": 1137, "y": 69662, "w": 26, "h": 245, "m": 40, "t": 30}, {"x": 2158, "y": 69684, "w": 26, "h": 233, "m": 67, "t": 57}, {"x": 2610, "y": 69684, "w": 26, "h": 233, "m": 79, "t": 69}, {"x": 303, "y": 69688, "w": 28, "h": 27, "m": 18, "t": 8}, {"x": 3626, "y": 69780, "w": 27, "h": 64, "m": 106, "t": 96}, {"x": 227, "y": 69881, "w": 28, "h": 52, "m": 16, "t": 6}, {"x": 1440, "y": 69928, "w": 26, "h": 87, "m": 48, "t": 38}, {"x": 1590, "y": 69928, "w": 27, "h": 98, "m": 52, "t": 42}, {"x": 1816, "y": 69928, "w": 26, "h": 86, "m": 58, "t": 48}, {"x": 3664, "y": 70102, "w": 27, "h": 50, "m": 107, "t": 97}, {"x": 3815, "y": 70113, "w": 26, "h": 75, "m": 111, "t": 101}, {"x": 266, "y": 70226, "w": 27, "h": 28, "m": 17, "t": 7}, {"x": 341, "y": 70227, "w": 27, "h": 27, "m": 19, "t": 9}, {"x": 1060, "y": 70249, "w": 27, "h": 158, "m": 38, "t": 28}, {"x": 2723, "y": 70257, "w": 27, "h": 431, "m": 82, "t": 72}, {"x": 2271, "y": 70258, "w": 26, "h": 419, "m": 70, "t": 60}, {"x": 3627, "y": 70268, "w": 27, "h": 52, "m": 106, "t": 96}, {"x": 304, "y": 70286, "w": 27, "h": 28, "m": 18, "t": 8}, {"x": 1364, "y": 70509, "w": 26, "h": 251, "m": 46, "t": 36}, {"x": 1628, "y": 70510, "w": 27, "h": 204, "m": 53, "t": 43}, {"x": 227, "y": 70535, "w": 28, "h": 40, "m": 16, "t": 6}, {"x": 3778, "y": 70577, "w": 26, "h": 62, "m": 110, "t": 100}, {"x": 1515, "y": 70722, "w": 26, "h": 110, "m": 50, "t": 40}, {"x": 1816, "y": 70722, "w": 27, "h": 144, "m": 58, "t": 48}, {"x": 266, "y": 70771, "w": 27, "h": 51, "m": 17, "t": 7}, {"x": 2270, "y": 70816, "w": 27, "h": 189, "m": 70, "t": 60}, {"x": 2722, "y": 70825, "w": 27, "h": 179, "m": 82, "t": 72}, {"x": 3814, "y": 70836, "w": 27, "h": 61, "m": 111, "t": 101}, {"x": 1627, "y": 71017, "w": 27, "h": 97, "m": 53, "t": 43}, {"x": 1816, "y": 71052, "w": 26, "h": 73, "m": 58, "t": 48}, {"x": 1967, "y": 71063, "w": 27, "h": 73, "m": 62, "t": 52}, {"x": 227, "y": 71066, "w": 27, "h": 61, "m": 16, "t": 6}, {"x": 2685, "y": 71131, "w": 27, "h": 181, "m": 81, "t": 71}, {"x": 2234, "y": 71144, "w": 26, "h": 169, "m": 69, "t": 59}, {"x": 3778, "y": 71259, "w": 27, "h": 52, "m": 110, "t": 100}, {"x": 266, "y": 71313, "w": 27, "h": 50, "m": 17, "t": 7}, {"x": 341, "y": 71325, "w": 28, "h": 38, "m": 19, "t": 9}, {"x": 3665, "y": 71355, "w": 27, "h": 63, "m": 107, "t": 97}, {"x": 796, "y": 71370, "w": 27, "h": 192, "m": 31, "t": 21}, {"x": 304, "y": 71395, "w": 27, "h": 27, "m": 18, "t": 8}, {"x": 2159, "y": 71415, "w": 26, "h": 216, "m": 67, "t": 57}, {"x": 3815, "y": 71426, "w": 27, "h": 62, "m": 111, "t": 101}, {"x": 2611, "y": 71427, "w": 27, "h": 204, "m": 79, "t": 69}, {"x": 3627, "y": 71508, "w": 27, "h": 52, "m": 106, "t": 96}, {"x": 3778, "y": 71626, "w": 27, "h": 52, "m": 110, "t": 100}, {"x": 228, "y": 71630, "w": 27, "h": 52, "m": 16, "t": 6}, {"x": 1251, "y": 71712, "w": 27, "h": 86, "m": 43, "t": 33}, {"x": 1516, "y": 71712, "w": 26, "h": 87, "m": 50, "t": 40}, {"x": 1704, "y": 71712, "w": 26, "h": 86, "m": 55, "t": 45}, {"x": 1968, "y": 71723, "w": 27, "h": 123, "m": 62, "t": 52}, {"x": 2422, "y": 71723, "w": 27, "h": 122, "m": 74, "t": 64}, {"x": 266, "y": 71951, "w": 27, "h": 73, "m": 17, "t": 7}, {"x": 3664, "y": 71958, "w": 28, "h": 63, "m": 107, "t": 97}, {"x": 341, "y": 71962, "w": 27, "h": 63, "m": 19, "t": 9}, {"x": 795, "y": 71985, "w": 27, "h": 229, "m": 31, "t": 21}, {"x": 2535, "y": 72043, "w": 26, "h": 749, "m": 77, "t": 67}, {"x": 2082, "y": 72044, "w": 27, "h": 808, "m": 65, "t": 55}, {"x": 3815, "y": 72054, "w": 26, "h": 74, "m": 111, "t": 101}, {"x": 303, "y": 72069, "w": 27, "h": 51, "m": 18, "t": 8}, {"x": 3626, "y": 72137, "w": 28, "h": 50, "m": 106, "t": 96}, {"x": 227, "y": 72283, "w": 27, "h": 50, "m": 16, "t": 6}, {"x": 1439, "y": 72316, "w": 27, "h": 74, "m": 48, "t": 38}, {"x": 1250, "y": 72317, "w": 26, "h": 73, "m": 43, "t": 33}, {"x": 1364, "y": 72317, "w": 26, "h": 73, "m": 46, "t": 36}, {"x": 266, "y": 72532, "w": 27, "h": 51, "m": 17, "t": 7}, {"x": 1364, "y": 72566, "w": 26, "h": 86, "m": 46, "t": 36}, {"x": 1440, "y": 72566, "w": 26, "h": 86, "m": 48, "t": 38}, {"x": 1703, "y": 72577, "w": 26, "h": 87, "m": 55, "t": 45}, {"x": 3777, "y": 72752, "w": 27, "h": 63, "m": 110, "t": 100}, {"x": 227, "y": 72756, "w": 27, "h": 51, "m": 16, "t": 6}, {"x": 1439, "y": 72849, "w": 27, "h": 74, "m": 48, "t": 38}, {"x": 1702, "y": 72849, "w": 27, "h": 62, "m": 55, "t": 45}, {"x": 1815, "y": 72849, "w": 27, "h": 62, "m": 58, "t": 48}, {"x": 264, "y": 73038, "w": 28, "h": 62, "m": 17, "t": 7}, {"x": 340, "y": 73038, "w": 27, "h": 62, "m": 19, "t": 9}, {"x": 983, "y": 73084, "w": 28, "h": 121, "m": 36, "t": 26}, {"x": 2496, "y": 73094, "w": 27, "h": 227, "m": 76, "t": 66}, {"x": 3814, "y": 73104, "w": 27, "h": 63, "m": 111, "t": 101}, {"x": 2043, "y": 73105, "w": 27, "h": 215, "m": 64, "t": 54}, {"x": 302, "y": 73120, "w": 28, "h": 39, "m": 18, "t": 8}, {"x": 226, "y": 73331, "w": 27, "h": 50, "m": 16, "t": 6}, {"x": 1249, "y": 73341, "w": 27, "h": 98, "m": 43, "t": 33}, {"x": 1438, "y": 73341, "w": 27, "h": 110, "m": 48, "t": 38}, {"x": 1363, "y": 73342, "w": 26, "h": 109, "m": 46, "t": 36}, {"x": 1589, "y": 73342, "w": 27, "h": 109, "m": 52, "t": 42}, {"x": 150, "y": 73415, "w": 28, "h": 62, "m": 14, "t": 4}, {"x": 3663, "y": 73539, "w": 27, "h": 50, "m": 107, "t": 97}, {"x": 3700, "y": 73550, "w": 28, "h": 27, "m": 108, "t": 98}, {"x": 3776, "y": 73550, "w": 27, "h": 62, "m": 110, "t": 100}, {"x": 264, "y": 73555, "w": 28, "h": 62, "m": 17, "t": 7}, {"x": 340, "y": 73555, "w": 27, "h": 86, "m": 19, "t": 9}, {"x": 1058, "y": 73588, "w": 27, "h": 243, "m": 38, "t": 28}, {"x": 1514, "y": 73588, "w": 26, "h": 242, "m": 50, "t": 40}, {"x": 2533, "y": 73622, "w": 27, "h": 361, "m": 77, "t": 67}, {"x": 2081, "y": 73624, "w": 27, "h": 348, "m": 65, "t": 55}, {"x": 3813, "y": 73633, "w": 27, "h": 51, "m": 111, "t": 101}, {"x": 302, "y": 73638, "w": 27, "h": 62, "m": 18, "t": 8}, {"x": 3625, "y": 73741, "w": 27, "h": 63, "m": 106, "t": 96}, {"x": 1626, "y": 73864, "w": 27, "h": 97, "m": 53, "t": 43}, {"x": 1965, "y": 73874, "w": 27, "h": 99, "m": 62, "t": 52}, {"x": 1777, "y": 73875, "w": 26, "h": 86, "m": 57, "t": 47}, {"x": 225, "y": 73877, "w": 28, "h": 62, "m": 16, "t": 6}, {"x": 3775, "y": 73895, "w": 27, "h": 62, "m": 110, "t": 100}, {"x": 263, "y": 74101, "w": 27, "h": 63, "m": 17, "t": 7}, {"x": 339, "y": 74101, "w": 27, "h": 75, "m": 19, "t": 9}, {"x": 982, "y": 74136, "w": 28, "h": 122, "m": 36, "t": 26}, {"x": 1437, "y": 74159, "w": 27, "h": 110, "m": 48, "t": 38}, {"x": 2155, "y": 74181, "w": 27, "h": 121, "m": 67, "t": 57}, {"x": 301, "y": 74184, "w": 27, "h": 51, "m": 18, "t": 8}, {"x": 2607, "y": 74192, "w": 27, "h": 109, "m": 79, "t": 69}, {"x": 149, "y": 74371, "w": 27, "h": 62, "m": 14, "t": 4}, {"x": 224, "y": 74429, "w": 27, "h": 51, "m": 16, "t": 6}, {"x": 1625, "y": 74464, "w": 26, "h": 86, "m": 53, "t": 43}, {"x": 2682, "y": 74473, "w": 27, "h": 86, "m": 81, "t": 71}, {"x": 2230, "y": 74474, "w": 27, "h": 86, "m": 69, "t": 59}, {"x": 1775, "y": 74475, "w": 27, "h": 74, "m": 57, "t": 47}, {"x": 2079, "y": 74475, "w": 27, "h": 73, "m": 65, "t": 55}, {"x": 262, "y": 74678, "w": 27, "h": 75, "m": 17, "t": 7}, {"x": 338, "y": 74678, "w": 27, "h": 64, "m": 19, "t": 9}, {"x": 2719, "y": 74746, "w": 27, "h": 97, "m": 82, "t": 72}, {"x": 2267, "y": 74747, "w": 27, "h": 108, "m": 70, "t": 60}, {"x": 1360, "y": 74748, "w": 27, "h": 121, "m": 46, "t": 36}, {"x": 905, "y": 74761, "w": 27, "h": 97, "m": 34, "t": 24}, {"x": 300, "y": 74774, "w": 27, "h": 38, "m": 18, "t": 8}, {"x": 2342, "y": 74922, "w": 26, "h": 98, "m": 72, "t": 62}, {"x": 2795, "y": 74922, "w": 27, "h": 85, "m": 84, "t": 74}, {"x": 1964, "y": 75051, "w": 26, "h": 97, "m": 62, "t": 52}, {"x": 2079, "y": 75051, "w": 26, "h": 97, "m": 65, "t": 55}, {"x": 2870, "y": 75061, "w": 27, "h": 86, "m": 86, "t": 76}, {"x": 2418, "y": 75062, "w": 27, "h": 86, "m": 74, "t": 64}, {"x": 1699, "y": 75064, "w": 27, "h": 85, "m": 55, "t": 45}, {"x": 3698, "y": 75107, "w": 27, "h": 27, "m": 108, "t": 98}, {"x": 337, "y": 75182, "w": 27, "h": 170, "m": 19, "t": 9}, {"x": 2493, "y": 75191, "w": 26, "h": 87, "m": 76, "t": 66}, {"x": 2945, "y": 75191, "w": 27, "h": 86, "m": 88, "t": 78}, {"x": 3698, "y": 75226, "w": 27, "h": 169, "m": 108, "t": 98}, {"x": 866, "y": 75288, "w": 27, "h": 239, "m": 33, "t": 23}, {"x": 1321, "y": 75359, "w": 27, "h": 215, "m": 45, "t": 35}, {"x": 299, "y": 75384, "w": 27, "h": 37, "m": 18, "t": 8}, {"x": 2983, "y": 75390, "w": 27, "h": 703, "m": 89, "t": 79}, {"x": 2530, "y": 75404, "w": 27, "h": 690, "m": 77, "t": 67}, {"x": 3735, "y": 75426, "w": 27, "h": 63, "m": 109, "t": 99}, {"x": 2077, "y": 75653, "w": 27, "h": 123, "m": 65, "t": 55}, {"x": 1773, "y": 75654, "w": 27, "h": 100, "m": 57, "t": 47}, {"x": 222, "y": 75655, "w": 27, "h": 51, "m": 16, "t": 6}, {"x": 1886, "y": 75665, "w": 27, "h": 100, "m": 60, "t": 50}, {"x": 3808, "y": 75723, "w": 27, "h": 61, "m": 111, "t": 101}, {"x": 1885, "y": 75891, "w": 27, "h": 87, "m": 60, "t": 50}, {"x": 2227, "y": 75902, "w": 27, "h": 98, "m": 69, "t": 59}, {"x": 2076, "y": 75903, "w": 27, "h": 87, "m": 65, "t": 55}, {"x": 259, "y": 76120, "w": 27, "h": 74, "m": 17, "t": 7}, {"x": 3771, "y": 76136, "w": 26, "h": 98, "m": 110, "t": 100}, {"x": 3695, "y": 76148, "w": 27, "h": 74, "m": 108, "t": 98}, {"x": 2339, "y": 76150, "w": 26, "h": 75, "m": 72, "t": 62}, {"x": 2075, "y": 76151, "w": 27, "h": 75, "m": 65, "t": 55}, {"x": 2226, "y": 76151, "w": 27, "h": 74, "m": 69, "t": 59}, {"x": 2980, "y": 76243, "w": 27, "h": 314, "m": 89, "t": 79}, {"x": 2527, "y": 76244, "w": 27, "h": 326, "m": 77, "t": 67}, {"x": 787, "y": 76452, "w": 27, "h": 298, "m": 31, "t": 21}, {"x": 3807, "y": 76470, "w": 27, "h": 50, "m": 111, "t": 101}, {"x": 3657, "y": 76493, "w": 26, "h": 39, "m": 107, "t": 97}, {"x": 1242, "y": 76498, "w": 27, "h": 275, "m": 43, "t": 33}, {"x": 219, "y": 76524, "w": 28, "h": 52, "m": 16, "t": 6}, {"x": 2488, "y": 76568, "w": 27, "h": 225, "m": 76, "t": 66}, {"x": 2941, "y": 76591, "w": 27, "h": 202, "m": 88, "t": 78}, {"x": 3618, "y": 76647, "w": 27, "h": 62, "m": 106, "t": 96}, {"x": 3769, "y": 76740, "w": 27, "h": 63, "m": 110, "t": 100}, {"x": 2074, "y": 76827, "w": 26, "h": 143, "m": 65, "t": 55}, {"x": 2865, "y": 76894, "w": 26, "h": 394, "m": 86, "t": 76}, {"x": 2261, "y": 76895, "w": 27, "h": 86, "m": 70, "t": 60}, {"x": 2413, "y": 76896, "w": 27, "h": 405, "m": 74, "t": 64}, {"x": 256, "y": 76937, "w": 27, "h": 62, "m": 17, "t": 7}, {"x": 975, "y": 77212, "w": 27, "h": 283, "m": 36, "t": 26}, {"x": 3655, "y": 77213, "w": 27, "h": 50, "m": 107, "t": 97}, {"x": 1430, "y": 77241, "w": 26, "h": 265, "m": 48, "t": 38}, {"x": 217, "y": 77268, "w": 27, "h": 63, "m": 16, "t": 6}, {"x": 2675, "y": 77298, "w": 27, "h": 240, "m": 81, "t": 71}, {"x": 2224, "y": 77299, "w": 26, "h": 239, "m": 69, "t": 59}, {"x": 3805, "y": 77308, "w": 27, "h": 62, "m": 111, "t": 101}, {"x": 3616, "y": 77402, "w": 28, "h": 63, "m": 106, "t": 96}, {"x": 1881, "y": 77620, "w": 26, "h": 123, "m": 60, "t": 50}, {"x": 2071, "y": 77620, "w": 27, "h": 135, "m": 65, "t": 55}, {"x": 1768, "y": 77621, "w": 26, "h": 123, "m": 57, "t": 47}, {"x": 1880, "y": 77823, "w": 26, "h": 86, "m": 60, "t": 50}, {"x": 2070, "y": 77824, "w": 27, "h": 97, "m": 65, "t": 55}, {"x": 3690, "y": 77877, "w": 27, "h": 40, "m": 108, "t": 98}, {"x": 3765, "y": 77877, "w": 27, "h": 39, "m": 110, "t": 100}, {"x": 2334, "y": 77918, "w": 26, "h": 181, "m": 72, "t": 62}, {"x": 3728, "y": 77925, "w": 26, "h": 62, "m": 109, "t": 99}, {"x": 2787, "y": 77929, "w": 26, "h": 168, "m": 84, "t": 74}, {"x": 253, "y": 78066, "w": 27, "h": 62, "m": 17, "t": 7}, {"x": 2333, "y": 78200, "w": 26, "h": 75, "m": 72, "t": 62}, {"x": 2220, "y": 78201, "w": 27, "h": 74, "m": 69, "t": 59}, {"x": 3802, "y": 78207, "w": 27, "h": 63, "m": 111, "t": 101}, {"x": 2069, "y": 78214, "w": 27, "h": 62, "m": 65, "t": 55}, {"x": 3651, "y": 78374, "w": 27, "h": 63, "m": 107, "t": 97}, {"x": 327, "y": 78445, "w": 28, "h": 75, "m": 19, "t": 9}, {"x": 3764, "y": 78456, "w": 27, "h": 51, "m": 110, "t": 100}, {"x": 3688, "y": 78457, "w": 28, "h": 50, "m": 108, "t": 98}, {"x": 971, "y": 78466, "w": 27, "h": 206, "m": 36, "t": 26}, {"x": 1426, "y": 78500, "w": 26, "h": 170, "m": 48, "t": 38}, {"x": 3801, "y": 78516, "w": 27, "h": 51, "m": 111, "t": 101}, {"x": 2483, "y": 78521, "w": 27, "h": 227, "m": 76, "t": 66}, {"x": 2030, "y": 78523, "w": 27, "h": 226, "m": 64, "t": 54}, {"x": 290, "y": 78541, "w": 27, "h": 51, "m": 18, "t": 8}, {"x": 3613, "y": 78564, "w": 27, "h": 62, "m": 106, "t": 96}, {"x": 1801, "y": 78804, "w": 27, "h": 87, "m": 58, "t": 48}, {"x": 2030, "y": 78805, "w": 26, "h": 85, "m": 64, "t": 54}, {"x": 1877, "y": 78806, "w": 27, "h": 84, "m": 60, "t": 50}, {"x": 213, "y": 78812, "w": 27, "h": 51, "m": 16, "t": 6}, {"x": 3648, "y": 78930, "w": 27, "h": 53, "m": 107, "t": 97}, {"x": 476, "y": 79022, "w": 28, "h": 63, "m": 23, "t": 13}, {"x": 250, "y": 79023, "w": 27, "h": 73, "m": 17, "t": 7}, {"x": 326, "y": 79023, "w": 27, "h": 62, "m": 19, "t": 9}, {"x": 1159, "y": 79065, "w": 27, "h": 192, "m": 41, "t": 31}, {"x": 1613, "y": 79065, "w": 27, "h": 179, "m": 53, "t": 43}, {"x": 2520, "y": 79083, "w": 27, "h": 359, "m": 77, "t": 67}, {"x": 2067, "y": 79085, "w": 27, "h": 168, "m": 65, "t": 55}, {"x": 3612, "y": 79102, "w": 27, "h": 63, "m": 106, "t": 96}, {"x": 288, "y": 79116, "w": 27, "h": 51, "m": 18, "t": 8}, {"x": 2067, "y": 79357, "w": 27, "h": 87, "m": 65, "t": 55}, {"x": 1763, "y": 79358, "w": 27, "h": 87, "m": 57, "t": 47}, {"x": 1876, "y": 79358, "w": 27, "h": 99, "m": 60, "t": 50}, {"x": 326, "y": 79566, "w": 26, "h": 62, "m": 19, "t": 9}, {"x": 1574, "y": 79632, "w": 27, "h": 122, "m": 52, "t": 42}, {"x": 1121, "y": 79633, "w": 27, "h": 109, "m": 40, "t": 30}, {"x": 288, "y": 79661, "w": 27, "h": 39, "m": 18, "t": 8}, {"x": 3762, "y": 79777, "w": 27, "h": 109, "m": 110, "t": 100}, {"x": 3686, "y": 79778, "w": 27, "h": 109, "m": 108, "t": 98}, {"x": 2066, "y": 79879, "w": 27, "h": 63, "m": 65, "t": 55}, {"x": 1951, "y": 79880, "w": 27, "h": 63, "m": 62, "t": 52}, {"x": 1762, "y": 79881, "w": 27, "h": 62, "m": 57, "t": 47}, {"x": 2971, "y": 79909, "w": 27, "h": 170, "m": 89, "t": 79}, {"x": 2518, "y": 79912, "w": 27, "h": 158, "m": 77, "t": 67}, {"x": 325, "y": 80053, "w": 26, "h": 98, "m": 19, "t": 9}, {"x": 1043, "y": 80146, "w": 27, "h": 97, "m": 38, "t": 28}, {"x": 1498, "y": 80155, "w": 27, "h": 98, "m": 50, "t": 40}, {"x": 287, "y": 80184, "w": 27, "h": 39, "m": 18, "t": 8}, {"x": 2971, "y": 80194, "w": 27, "h": 145, "m": 89, "t": 79}, {"x": 2518, "y": 80196, "w": 27, "h": 158, "m": 77, "t": 67}, {"x": 3803, "y": 80216, "w": 26, "h": 61, "m": 111, "t": 101}, {"x": 1951, "y": 80413, "w": 27, "h": 85, "m": 62, "t": 52}, {"x": 1762, "y": 80414, "w": 27, "h": 74, "m": 57, "t": 47}, {"x": 2066, "y": 80424, "w": 27, "h": 74, "m": 65, "t": 55}, {"x": 2971, "y": 80465, "w": 27, "h": 146, "m": 89, "t": 79}, {"x": 2518, "y": 80468, "w": 27, "h": 145, "m": 77, "t": 67}, {"x": 3761, "y": 80475, "w": 27, "h": 63, "m": 110, "t": 100}, {"x": 325, "y": 80562, "w": 27, "h": 98, "m": 19, "t": 9}, {"x": 3686, "y": 80616, "w": 27, "h": 93, "m": 108, "t": 98}, {"x": 3649, "y": 80651, "w": 28, "h": 53, "m": 107, "t": 97}, {"x": 1423, "y": 80663, "w": 27, "h": 295, "m": 48, "t": 38}, {"x": 968, "y": 80665, "w": 27, "h": 295, "m": 36, "t": 26}, {"x": 287, "y": 80691, "w": 27, "h": 37, "m": 18, "t": 8}, {"x": 2971, "y": 80712, "w": 27, "h": 677, "m": 89, "t": 79}, {"x": 2519, "y": 80715, "w": 26, "h": 687, "m": 77, "t": 67}, {"x": 3611, "y": 80815, "w": 27, "h": 64, "m": 106, "t": 96}, {"x": 2066, "y": 80951, "w": 27, "h": 74, "m": 65, "t": 55}, {"x": 1951, "y": 80952, "w": 27, "h": 74, "m": 62, "t": 52}, {"x": 1762, "y": 80953, "w": 27, "h": 74, "m": 57, "t": 47}, {"x": 324, "y": 81136, "w": 27, "h": 98, "m": 19, "t": 9}, {"x": 1347, "y": 81226, "w": 27, "h": 99, "m": 46, "t": 36}, {"x": 892, "y": 81228, "w": 27, "h": 110, "m": 34, "t": 24}, {"x": 287, "y": 81256, "w": 27, "h": 27, "m": 18, "t": 8}, {"x": 3804, "y": 81290, "w": 27, "h": 54, "m": 111, "t": 101}, {"x": 1800, "y": 81510, "w": 27, "h": 85, "m": 58, "t": 48}, {"x": 2972, "y": 81515, "w": 26, "h": 167, "m": 89, "t": 79}, {"x": 2519, "y": 81518, "w": 27, "h": 167, "m": 77, "t": 67}, {"x": 1951, "y": 81521, "w": 28, "h": 74, "m": 62, "t": 52}, {"x": 2067, "y": 81521, "w": 26, "h": 73, "m": 65, "t": 55}, {"x": 325, "y": 81690, "w": 27, "h": 111, "m": 19, "t": 9}, {"x": 3686, "y": 81711, "w": 27, "h": 97, "m": 108, "t": 98}, {"x": 3762, "y": 81721, "w": 27, "h": 64, "m": 110, "t": 100}, {"x": 1310, "y": 81792, "w": 27, "h": 110, "m": 45, "t": 35}, {"x": 855, "y": 81794, "w": 27, "h": 98, "m": 33, "t": 23}, {"x": 3798, "y": 81813, "w": 26, "h": 64, "m": 111, "t": 101}, {"x": 2972, "y": 81818, "w": 27, "h": 183, "m": 89, "t": 79}, {"x": 2519, "y": 81821, "w": 27, "h": 182, "m": 77, "t": 67}, {"x": 287, "y": 81845, "w": 28, "h": 39, "m": 18, "t": 8}, {"x": 1952, "y": 82086, "w": 27, "h": 87, "m": 62, "t": 52}, {"x": 1763, "y": 82088, "w": 27, "h": 87, "m": 57, "t": 47}, {"x": 2067, "y": 82099, "w": 27, "h": 74, "m": 65, "t": 55}, {"x": 2972, "y": 82104, "w": 27, "h": 182, "m": 89, "t": 79}, {"x": 3763, "y": 82114, "w": 27, "h": 62, "m": 110, "t": 100}, {"x": 2520, "y": 82119, "w": 26, "h": 181, "m": 77, "t": 67}, {"x": 326, "y": 82284, "w": 27, "h": 123, "m": 19, "t": 9}, {"x": 3687, "y": 82350, "w": 27, "h": 97, "m": 108, "t": 98}, {"x": 780, "y": 82365, "w": 26, "h": 275, "m": 31, "t": 21}, {"x": 3650, "y": 82385, "w": 27, "h": 63, "m": 107, "t": 97}, {"x": 1235, "y": 82410, "w": 26, "h": 261, "m": 43, "t": 33}, {"x": 288, "y": 82438, "w": 27, "h": 86, "m": 18, "t": 8}, {"x": 2520, "y": 82449, "w": 26, "h": 780, "m": 77, "t": 67}, {"x": 3725, "y": 82455, "w": 26, "h": 74, "m": 109, "t": 99}, {"x": 2973, "y": 82458, "w": 26, "h": 768, "m": 89, "t": 79}, {"x": 3612, "y": 82551, "w": 27, "h": 62, "m": 106, "t": 96}, {"x": 3800, "y": 82737, "w": 27, "h": 62, "m": 111, "t": 101}, {"x": 1953, "y": 82747, "w": 26, "h": 133, "m": 62, "t": 52}, {"x": 1801, "y": 82748, "w": 27, "h": 133, "m": 58, "t": 48}, {"x": 2068, "y": 82758, "w": 27, "h": 121, "m": 65, "t": 55}, {"x": 212, "y": 82791, "w": 27, "h": 63, "m": 16, "t": 6}, {"x": 3764, "y": 83006, "w": 27, "h": 63, "m": 110, "t": 100}, {"x": 251, "y": 83050, "w": 27, "h": 63, "m": 17, "t": 7}, {"x": 1954, "y": 83064, "w": 26, "h": 97, "m": 62, "t": 52}, {"x": 2257, "y": 83074, "w": 26, "h": 97, "m": 70, "t": 60}, {"x": 2069, "y": 83076, "w": 26, "h": 84, "m": 65, "t": 55}, {"x": 2408, "y": 83347, "w": 27, "h": 85, "m": 74, "t": 64}, {"x": 3689, "y": 83351, "w": 27, "h": 63, "m": 108, "t": 98}, {"x": 2258, "y": 83359, "w": 26, "h": 74, "m": 70, "t": 60}, {"x": 2069, "y": 83361, "w": 27, "h": 73, "m": 65, "t": 55}, {"x": 214, "y": 83370, "w": 27, "h": 51, "m": 16, "t": 6}, {"x": 2974, "y": 83425, "w": 27, "h": 145, "m": 89, "t": 79}, {"x": 2522, "y": 83428, "w": 26, "h": 133, "m": 77, "t": 67}, {"x": 3802, "y": 83458, "w": 26, "h": 50, "m": 111, "t": 101}, {"x": 253, "y": 83654, "w": 27, "h": 75, "m": 17, "t": 7}, {"x": 328, "y": 83654, "w": 27, "h": 74, "m": 19, "t": 9}, {"x": 442, "y": 83658, "w": 25, "h": 59, "m": 22, "t": 12}, {"x": 3652, "y": 83718, "w": 27, "h": 62, "m": 107, "t": 97}, {"x": 896, "y": 83734, "w": 27, "h": 255, "m": 34, "t": 24}, {"x": 1351, "y": 83743, "w": 26, "h": 243, "m": 46, "t": 36}, {"x": 290, "y": 83761, "w": 27, "h": 39, "m": 18, "t": 8}, {"x": 2936, "y": 83782, "w": 27, "h": 195, "m": 88, "t": 78}, {"x": 2484, "y": 83796, "w": 27, "h": 195, "m": 76, "t": 66}, {"x": 3614, "y": 83873, "w": 27, "h": 64, "m": 106, "t": 96}, {"x": 215, "y": 84142, "w": 27, "h": 63, "m": 16, "t": 6}, {"x": 2862, "y": 84150, "w": 27, "h": 145, "m": 86, "t": 76}, {"x": 2410, "y": 84152, "w": 27, "h": 157, "m": 74, "t": 64}, {"x": 2070, "y": 84155, "w": 27, "h": 98, "m": 65, "t": 55}, {"x": 1956, "y": 84156, "w": 26, "h": 98, "m": 62, "t": 52}, {"x": 1690, "y": 84157, "w": 27, "h": 99, "m": 55, "t": 45}, {"x": 1804, "y": 84157, "w": 27, "h": 98, "m": 58, "t": 48}, {"x": 3766, "y": 84203, "w": 27, "h": 63, "m": 110, "t": 100}, {"x": 254, "y": 84414, "w": 27, "h": 87, "m": 17, "t": 7}, {"x": 330, "y": 84414, "w": 26, "h": 63, "m": 19, "t": 9}, {"x": 973, "y": 84445, "w": 27, "h": 301, "m": 36, "t": 26}, {"x": 3654, "y": 84487, "w": 27, "h": 39, "m": 107, "t": 97}, {"x": 1428, "y": 84489, "w": 27, "h": 254, "m": 48, "t": 38}, {"x": 292, "y": 84521, "w": 27, "h": 39, "m": 18, "t": 8}, {"x": 2222, "y": 84545, "w": 27, "h": 311, "m": 69, "t": 59}, {"x": 2674, "y": 84554, "w": 27, "h": 299, "m": 81, "t": 71}, {"x": 3804, "y": 84560, "w": 27, "h": 63, "m": 111, "t": 101}, {"x": 3616, "y": 84620, "w": 27, "h": 62, "m": 106, "t": 96}, {"x": 216, "y": 84771, "w": 27, "h": 62, "m": 16, "t": 6}, {"x": 2072, "y": 84888, "w": 27, "h": 86, "m": 65, "t": 55}, {"x": 1881, "y": 84889, "w": 27, "h": 87, "m": 60, "t": 50}, {"x": 1768, "y": 84890, "w": 27, "h": 87, "m": 57, "t": 47}, {"x": 2073, "y": 85125, "w": 27, "h": 99, "m": 65, "t": 55}, {"x": 1882, "y": 85126, "w": 27, "h": 87, "m": 60, "t": 50}, {"x": 2224, "y": 85135, "w": 26, "h": 135, "m": 69, "t": 59}, {"x": 3693, "y": 85150, "w": 27, "h": 64, "m": 108, "t": 98}, {"x": 2336, "y": 85207, "w": 27, "h": 264, "m": 72, "t": 62}, {"x": 2790, "y": 85216, "w": 26, "h": 275, "m": 84, "t": 74}, {"x": 3730, "y": 85221, "w": 27, "h": 39, "m": 109, "t": 99}, {"x": 256, "y": 85375, "w": 27, "h": 63, "m": 17, "t": 7}, {"x": 2225, "y": 85538, "w": 27, "h": 63, "m": 69, "t": 59}, {"x": 2337, "y": 85539, "w": 27, "h": 61, "m": 72, "t": 62}, {"x": 2074, "y": 85541, "w": 27, "h": 73, "m": 65, "t": 55}, {"x": 3657, "y": 85824, "w": 27, "h": 51, "m": 107, "t": 97}, {"x": 3694, "y": 85836, "w": 28, "h": 51, "m": 108, "t": 98}, {"x": 976, "y": 85867, "w": 27, "h": 207, "m": 36, "t": 26}, {"x": 2489, "y": 85892, "w": 26, "h": 276, "m": 76, "t": 66}, {"x": 2036, "y": 85896, "w": 27, "h": 275, "m": 64, "t": 54}, {"x": 1431, "y": 85900, "w": 27, "h": 194, "m": 48, "t": 38}, {"x": 3732, "y": 85907, "w": 27, "h": 51, "m": 109, "t": 99}, {"x": 295, "y": 85921, "w": 27, "h": 51, "m": 18, "t": 8}, {"x": 3620, "y": 85991, "w": 27, "h": 63, "m": 106, "t": 96}, {"x": 219, "y": 86134, "w": 27, "h": 63, "m": 16, "t": 6}, {"x": 2037, "y": 86226, "w": 26, "h": 75, "m": 64, "t": 54}, {"x": 1884, "y": 86228, "w": 27, "h": 75, "m": 60, "t": 50}, {"x": 1809, "y": 86229, "w": 27, "h": 74, "m": 58, "t": 48}, {"x": 3659, "y": 86462, "w": 27, "h": 40, "m": 107, "t": 97}, {"x": 485, "y": 86474, "w": 27, "h": 51, "m": 23, "t": 13}, {"x": 3696, "y": 86474, "w": 28, "h": 39, "m": 108, "t": 98}, {"x": 259, "y": 86499, "w": 27, "h": 28, "m": 17, "t": 7}, {"x": 335, "y": 86499, "w": 27, "h": 27, "m": 19, "t": 9}, {"x": 1621, "y": 86514, "w": 27, "h": 214, "m": 53, "t": 43}, {"x": 1167, "y": 86516, "w": 28, "h": 214, "m": 41, "t": 31}, {"x": 3734, "y": 86533, "w": 27, "h": 62, "m": 109, "t": 99}, {"x": 2529, "y": 86541, "w": 27, "h": 202, "m": 77, "t": 67}, {"x": 2076, "y": 86545, "w": 27, "h": 202, "m": 65, "t": 55}, {"x": 297, "y": 86559, "w": 27, "h": 27, "m": 18, "t": 8}, {"x": 3622, "y": 86639, "w": 27, "h": 62, "m": 106, "t": 96}, {"x": 2077, "y": 86803, "w": 27, "h": 97, "m": 65, "t": 55}, {"x": 1773, "y": 86805, "w": 27, "h": 84, "m": 57, "t": 47}, {"x": 1886, "y": 86815, "w": 27, "h": 62, "m": 60, "t": 50}, {"x": 260, "y": 87028, "w": 27, "h": 62, "m": 17, "t": 7}, {"x": 335, "y": 87028, "w": 27, "h": 62, "m": 19, "t": 9}, {"x": 1131, "y": 87080, "w": 27, "h": 193, "m": 40, "t": 30}, {"x": 1585, "y": 87089, "w": 27, "h": 194, "m": 52, "t": 42}, {"x": 298, "y": 87098, "w": 27, "h": 51, "m": 18, "t": 8}, {"x": 3697, "y": 87217, "w": 28, "h": 123, "m": 108, "t": 98}, {"x": 3773, "y": 87217, "w": 27, "h": 86, "m": 110, "t": 100}, {"x": 2530, "y": 87344, "w": 27, "h": 183, "m": 77, "t": 67}, {"x": 2078, "y": 87348, "w": 27, "h": 76, "m": 65, "t": 55}, {"x": 1887, "y": 87349, "w": 27, "h": 64, "m": 60, "t": 50}, {"x": 1774, "y": 87350, "w": 27, "h": 64, "m": 57, "t": 47}, {"x": 2983, "y": 87364, "w": 27, "h": 159, "m": 89, "t": 79}, {"x": 337, "y": 87574, "w": 27, "h": 63, "m": 19, "t": 9}, {"x": 262, "y": 87586, "w": 27, "h": 51, "m": 17, "t": 7}, {"x": 1056, "y": 87605, "w": 27, "h": 192, "m": 38, "t": 28}, {"x": 1511, "y": 87637, "w": 27, "h": 157, "m": 50, "t": 40}, {"x": 2984, "y": 87661, "w": 27, "h": 168, "m": 89, "t": 79}, {"x": 2531, "y": 87665, "w": 27, "h": 168, "m": 77, "t": 67}, {"x": 300, "y": 87669, "w": 27, "h": 28, "m": 18, "t": 8}, {"x": 3812, "y": 87676, "w": 28, "h": 55, "m": 111, "t": 101}, {"x": 2079, "y": 87904, "w": 27, "h": 97, "m": 65, "t": 55}, {"x": 1964, "y": 87905, "w": 27, "h": 97, "m": 62, "t": 52}, {"x": 1775, "y": 87906, "w": 27, "h": 85, "m": 57, "t": 47}, {"x": 3775, "y": 87927, "w": 27, "h": 62, "m": 110, "t": 100}, {"x": 2985, "y": 87931, "w": 26, "h": 168, "m": 89, "t": 79}, {"x": 2532, "y": 87935, "w": 27, "h": 168, "m": 77, "t": 67}, {"x": 3699, "y": 88080, "w": 27, "h": 110, "m": 108, "t": 98}, {"x": 3663, "y": 88127, "w": 25, "h": 64, "m": 107, "t": 97}, {"x": 338, "y": 88139, "w": 27, "h": 38, "m": 19, "t": 9}, {"x": 263, "y": 88140, "w": 27, "h": 50, "m": 17, "t": 7}, {"x": 981, "y": 88181, "w": 28, "h": 239, "m": 36, "t": 26}, {"x": 1437, "y": 88189, "w": 26, "h": 216, "m": 48, "t": 38}, {"x": 301, "y": 88197, "w": 27, "h": 51, "m": 18, "t": 8}, {"x": 2985, "y": 88202, "w": 27, "h": 688, "m": 89, "t": 79}, {"x": 2532, "y": 88205, "w": 27, "h": 700, "m": 77, "t": 67}, {"x": 3624, "y": 88293, "w": 28, "h": 74, "m": 106, "t": 96}, {"x": 1965, "y": 88457, "w": 27, "h": 87, "m": 62, "t": 52}, {"x": 2080, "y": 88468, "w": 27, "h": 75, "m": 65, "t": 55}, {"x": 1776, "y": 88470, "w": 27, "h": 75, "m": 57, "t": 47}, {"x": 264, "y": 88703, "w": 27, "h": 50, "m": 17, "t": 7}, {"x": 339, "y": 88714, "w": 27, "h": 39, "m": 19, "t": 9}, {"x": 3814, "y": 88740, "w": 27, "h": 60, "m": 111, "t": 101}, {"x": 1362, "y": 88743, "w": 27, "h": 192, "m": 46, "t": 36}, {"x": 907, "y": 88746, "w": 27, "h": 191, "m": 34, "t": 24}, {"x": 302, "y": 88774, "w": 27, "h": 38, "m": 18, "t": 8}, {"x": 1815, "y": 89034, "w": 27, "h": 72, "m": 58, "t": 48}, {"x": 3777, "y": 89038, "w": 27, "h": 85, "m": 110, "t": 100}, {"x": 2082, "y": 89043, "w": 27, "h": 73, "m": 65, "t": 55}, {"x": 1967, "y": 89044, "w": 27, "h": 73, "m": 62, "t": 52}, {"x": 2534, "y": 89052, "w": 27, "h": 181, "m": 77, "t": 67}, {"x": 2987, "y": 89061, "w": 27, "h": 170, "m": 89, "t": 79}, {"x": 3704, "y": 89241, "w": 26, "h": 93, "m": 108, "t": 98}, {"x": 265, "y": 89276, "w": 27, "h": 50, "m": 17, "t": 7}, {"x": 341, "y": 89276, "w": 27, "h": 62, "m": 19, "t": 9}, {"x": 3666, "y": 89278, "w": 27, "h": 50, "m": 107, "t": 97}, {"x": 1326, "y": 89331, "w": 26, "h": 227, "m": 45, "t": 35}, {"x": 871, "y": 89332, "w": 26, "h": 216, "m": 33, "t": 23}, {"x": 2987, "y": 89346, "w": 27, "h": 227, "m": 89, "t": 79}, {"x": 2535, "y": 89349, "w": 27, "h": 215, "m": 77, "t": 67}, {"x": 304, "y": 89360, "w": 27, "h": 38, "m": 18, "t": 8}, {"x": 3817, "y": 89370, "w": 26, "h": 60, "m": 111, "t": 101}, {"x": 3628, "y": 89457, "w": 27, "h": 47, "m": 106, "t": 96}, {"x": 2083, "y": 89657, "w": 26, "h": 75, "m": 65, "t": 55}, {"x": 1968, "y": 89658, "w": 27, "h": 63, "m": 62, "t": 52}, {"x": 1816, "y": 89659, "w": 27, "h": 63, "m": 58, "t": 48}, {"x": 3781, "y": 89661, "w": 26, "h": 70, "m": 110, "t": 100}, {"x": 2535, "y": 89666, "w": 27, "h": 157, "m": 77, "t": 67}, {"x": 2988, "y": 89676, "w": 27, "h": 145, "m": 89, "t": 79}, {"x": 266, "y": 89864, "w": 27, "h": 108, "m": 17, "t": 7}, {"x": 342, "y": 89875, "w": 27, "h": 98, "m": 19, "t": 9}, {"x": 3706, "y": 89898, "w": 26, "h": 88, "m": 108, "t": 98}, {"x": 3667, "y": 89934, "w": 27, "h": 56, "m": 107, "t": 97}, {"x": 796, "y": 89944, "w": 27, "h": 274, "m": 31, "t": 21}, {"x": 1251, "y": 89978, "w": 26, "h": 250, "m": 43, "t": 33}, {"x": 304, "y": 89993, "w": 27, "h": 38, "m": 18, "t": 8}, {"x": 454, "y": 90004, "w": 28, "h": 51, "m": 22, "t": 12}, {"x": 2989, "y": 90006, "w": 27, "h": 782, "m": 89, "t": 79}, {"x": 2536, "y": 90008, "w": 27, "h": 781, "m": 77, "t": 67}, {"x": 3745, "y": 90023, "w": 26, "h": 58, "m": 109, "t": 99}, {"x": 3630, "y": 90112, "w": 26, "h": 61, "m": 106, "t": 96}, {"x": 228, "y": 90216, "w": 27, "h": 62, "m": 16, "t": 6}, {"x": 3820, "y": 90283, "w": 27, "h": 54, "m": 111, "t": 101}, {"x": 2083, "y": 90304, "w": 27, "h": 110, "m": 65, "t": 55}, {"x": 1817, "y": 90305, "w": 27, "h": 99, "m": 58, "t": 48}, {"x": 1968, "y": 90305, "w": 27, "h": 109, "m": 62, "t": 52}, {"x": 3745, "y": 90431, "w": 26, "h": 26, "m": 109, "t": 99}, {"x": 3782, "y": 90591, "w": 26, "h": 61, "m": 110, "t": 100}, {"x": 1969, "y": 90623, "w": 27, "h": 74, "m": 62, "t": 52}, {"x": 2272, "y": 90633, "w": 26, "h": 74, "m": 70, "t": 60}, {"x": 2084, "y": 90635, "w": 27, "h": 73, "m": 65, "t": 55}, {"x": 266, "y": 90698, "w": 27, "h": 62, "m": 17, "t": 7}, {"x": 3704, "y": 90895, "w": 27, "h": 87, "m": 108, "t": 98}, {"x": 2272, "y": 90904, "w": 27, "h": 51, "m": 70, "t": 60}, {"x": 2423, "y": 90905, "w": 27, "h": 63, "m": 74, "t": 64}, {"x": 2084, "y": 90906, "w": 27, "h": 62, "m": 65, "t": 55}, {"x": 2989, "y": 90974, "w": 27, "h": 134, "m": 89, "t": 79}, {"x": 2536, "y": 90976, "w": 27, "h": 133, "m": 77, "t": 67}, {"x": 3668, "y": 91236, "w": 26, "h": 54, "m": 107, "t": 97}, {"x": 910, "y": 91263, "w": 26, "h": 251, "m": 34, "t": 24}, {"x": 1365, "y": 91263, "w": 27, "h": 239, "m": 46, "t": 36}, {"x": 228, "y": 91288, "w": 28, "h": 63, "m": 16, "t": 6}, {"x": 2498, "y": 91322, "w": 27, "h": 202, "m": 76, "t": 66}, {"x": 2950, "y": 91322, "w": 27, "h": 201, "m": 88, "t": 78}, {"x": 3821, "y": 91331, "w": 28, "h": 69, "m": 111, "t": 101}, {"x": 3627, "y": 91408, "w": 27, "h": 57, "m": 106, "t": 96}, {"x": 2422, "y": 91648, "w": 27, "h": 145, "m": 74, "t": 64}, {"x": 1703, "y": 91649, "w": 27, "h": 87, "m": 55, "t": 45}, {"x": 1816, "y": 91649, "w": 27, "h": 86, "m": 58, "t": 48}, {"x": 1968, "y": 91649, "w": 27, "h": 98, "m": 62, "t": 52}, {"x": 2083, "y": 91661, "w": 27, "h": 86, "m": 65, "t": 55}, {"x": 2875, "y": 91661, "w": 27, "h": 133, "m": 86, "t": 76}, {"x": 266, "y": 91709, "w": 27, "h": 62, "m": 17, "t": 7}, {"x": 3784, "y": 91753, "w": 27, "h": 63, "m": 110, "t": 100}, {"x": 985, "y": 91971, "w": 27, "h": 240, "m": 36, "t": 26}, {"x": 3670, "y": 91977, "w": 26, "h": 66, "m": 107, "t": 97}, {"x": 1440, "y": 91983, "w": 26, "h": 216, "m": 48, "t": 38}, {"x": 227, "y": 91995, "w": 28, "h": 63, "m": 16, "t": 6}, {"x": 2234, "y": 92030, "w": 27, "h": 288, "m": 69, "t": 59}, {"x": 2686, "y": 92042, "w": 27, "h": 276, "m": 81, "t": 71}, {"x": 3819, "y": 92062, "w": 26, "h": 65, "m": 111, "t": 101}, {"x": 3629, "y": 92171, "w": 26, "h": 64, "m": 106, "t": 96}, {"x": 1891, "y": 92397, "w": 27, "h": 122, "m": 60, "t": 50}, {"x": 1778, "y": 92398, "w": 27, "h": 109, "m": 57, "t": 47}, {"x": 2082, "y": 92398, "w": 27, "h": 109, "m": 65, "t": 55}, {"x": 1890, "y": 92634, "w": 27, "h": 85, "m": 60, "t": 50}, {"x": 2081, "y": 92647, "w": 27, "h": 96, "m": 65, "t": 55}, {"x": 2232, "y": 92670, "w": 27, "h": 96, "m": 69, "t": 59}, {"x": 3701, "y": 92684, "w": 27, "h": 27, "m": 108, "t": 98}, {"x": 2344, "y": 92716, "w": 27, "h": 181, "m": 72, "t": 62}, {"x": 2798, "y": 92717, "w": 26, "h": 192, "m": 84, "t": 74}, {"x": 3738, "y": 92746, "w": 27, "h": 23, "m": 109, "t": 99}, {"x": 2080, "y": 93011, "w": 27, "h": 87, "m": 65, "t": 55}, {"x": 2231, "y": 93012, "w": 27, "h": 85, "m": 69, "t": 59}, {"x": 2343, "y": 93012, "w": 27, "h": 86, "m": 72, "t": 62}, {"x": 3774, "y": 93062, "w": 25, "h": 59, "m": 110, "t": 100}, {"x": 262, "y": 93069, "w": 27, "h": 50, "m": 17, "t": 7}, {"x": 3660, "y": 93317, "w": 26, "h": 52, "m": 107, "t": 97}, {"x": 981, "y": 93354, "w": 27, "h": 261, "m": 36, "t": 26}, {"x": 1436, "y": 93366, "w": 27, "h": 250, "m": 48, "t": 38}, {"x": 2040, "y": 93379, "w": 27, "h": 249, "m": 64, "t": 54}, {"x": 2493, "y": 93379, "w": 27, "h": 238, "m": 76, "t": 66}, {"x": 223, "y": 93400, "w": 27, "h": 63, "m": 16, "t": 6}, {"x": 3811, "y": 93403, "w": 27, "h": 60, "m": 111, "t": 101}, {"x": 3623, "y": 93510, "w": 27, "h": 49, "m": 106, "t": 96}, {"x": 1811, "y": 93708, "w": 26, "h": 98, "m": 58, "t": 48}, {"x": 1886, "y": 93708, "w": 27, "h": 98, "m": 60, "t": 50}, {"x": 2038, "y": 93708, "w": 27, "h": 97, "m": 64, "t": 54}, {"x": 260, "y": 93812, "w": 27, "h": 63, "m": 17, "t": 7}, {"x": 3773, "y": 93828, "w": 26, "h": 50, "m": 110, "t": 100}, {"x": 1168, "y": 94015, "w": 27, "h": 265, "m": 41, "t": 31}, {"x": 1622, "y": 94016, "w": 27, "h": 277, "m": 53, "t": 43}, {"x": 3659, "y": 94017, "w": 27, "h": 63, "m": 107, "t": 97}, {"x": 221, "y": 94025, "w": 27, "h": 64, "m": 16, "t": 6}, {"x": 2529, "y": 94086, "w": 26, "h": 513, "m": 77, "t": 67}, {"x": 2076, "y": 94098, "w": 27, "h": 218, "m": 65, "t": 55}, {"x": 3809, "y": 94112, "w": 27, "h": 63, "m": 111, "t": 101}, {"x": 3621, "y": 94195, "w": 27, "h": 63, "m": 106, "t": 96}, {"x": 1771, "y": 94430, "w": 27, "h": 110, "m": 57, "t": 47}, {"x": 1884, "y": 94430, "w": 27, "h": 146, "m": 60, "t": 50}, {"x": 2075, "y": 94442, "w": 27, "h": 146, "m": 65, "t": 55}, {"x": 1884, "y": 94761, "w": 27, "h": 121, "m": 60, "t": 50}, {"x": 2075, "y": 94785, "w": 27, "h": 86, "m": 65, "t": 55}, {"x": 2226, "y": 94785, "w": 27, "h": 97, "m": 69, "t": 59}, {"x": 3771, "y": 94810, "w": 26, "h": 63, "m": 110, "t": 100}, {"x": 257, "y": 94817, "w": 27, "h": 63, "m": 17, "t": 7}, {"x": 3807, "y": 95129, "w": 27, "h": 62, "m": 111, "t": 101}, {"x": 2036, "y": 95138, "w": 27, "h": 308, "m": 64, "t": 54}, {"x": 2488, "y": 95139, "w": 27, "h": 319, "m": 76, "t": 66}, {"x": 219, "y": 95148, "w": 27, "h": 62, "m": 16, "t": 6}, {"x": 3656, "y": 95269, "w": 27, "h": 63, "m": 107, "t": 97}, {"x": 1127, "y": 95349, "w": 27, "h": 203, "m": 40, "t": 30}, {"x": 1581, "y": 95350, "w": 27, "h": 214, "m": 52, "t": 42}, {"x": 256, "y": 95360, "w": 27, "h": 50, "m": 17, "t": 7}, {"x": 3769, "y": 95362, "w": 27, "h": 50, "m": 110, "t": 100}, {"x": 2073, "y": 95444, "w": 27, "h": 167, "m": 65, "t": 55}, {"x": 2525, "y": 95455, "w": 27, "h": 168, "m": 77, "t": 67}, {"x": 3618, "y": 95456, "w": 27, "h": 51, "m": 106, "t": 96}, {"x": 3806, "y": 95527, "w": 26, "h": 61, "m": 111, "t": 101}, {"x": 217, "y": 95548, "w": 27, "h": 50, "m": 16, "t": 6}, {"x": 1767, "y": 95774, "w": 27, "h": 146, "m": 57, "t": 47}, {"x": 1880, "y": 95774, "w": 27, "h": 145, "m": 60, "t": 50}, {"x": 2147, "y": 95785, "w": 26, "h": 418, "m": 67, "t": 57}, {"x": 2599, "y": 95797, "w": 27, "h": 407, "m": 79, "t": 69}, {"x": 2071, "y": 95798, "w": 27, "h": 122, "m": 65, "t": 55}, {"x": 3767, "y": 95951, "w": 27, "h": 52, "m": 110, "t": 100}, {"x": 254, "y": 95952, "w": 27, "h": 51, "m": 17, "t": 7}, {"x": 3653, "y": 96046, "w": 27, "h": 51, "m": 107, "t": 97}, {"x": 1047, "y": 96155, "w": 27, "h": 170, "m": 38, "t": 28}, {"x": 1503, "y": 96178, "w": 26, "h": 146, "m": 50, "t": 40}, {"x": 3615, "y": 96200, "w": 27, "h": 63, "m": 106, "t": 96}, {"x": 2221, "y": 96201, "w": 27, "h": 494, "m": 69, "t": 59}, {"x": 2674, "y": 96201, "w": 26, "h": 565, "m": 81, "t": 71}, {"x": 3804, "y": 96260, "w": 26, "h": 62, "m": 111, "t": 101}, {"x": 215, "y": 96263, "w": 26, "h": 62, "m": 16, "t": 6}, {"x": 1766, "y": 96564, "w": 27, "h": 145, "m": 57, "t": 47}, {"x": 2070, "y": 96564, "w": 27, "h": 155, "m": 65, "t": 55}, {"x": 1954, "y": 96576, "w": 28, "h": 144, "m": 62, "t": 52}, {"x": 403, "y": 96603, "w": 27, "h": 50, "m": 21, "t": 11}, {"x": 1954, "y": 96894, "w": 27, "h": 134, "m": 62, "t": 52}, {"x": 2220, "y": 96894, "w": 27, "h": 121, "m": 69, "t": 59}, {"x": 2069, "y": 96906, "w": 27, "h": 110, "m": 65, "t": 55}, {"x": 3765, "y": 97020, "w": 27, "h": 50, "m": 110, "t": 100}, {"x": 251, "y": 97051, "w": 27, "h": 51, "m": 17, "t": 7}, {"x": 2521, "y": 97244, "w": 27, "h": 120, "m": 77, "t": 67}, {"x": 2068, "y": 97246, "w": 27, "h": 120, "m": 65, "t": 55}, {"x": 3801, "y": 97253, "w": 27, "h": 61, "m": 111, "t": 101}, {"x": 213, "y": 97274, "w": 27, "h": 63, "m": 16, "t": 6}, {"x": 3764, "y": 97381, "w": 27, "h": 50, "m": 110, "t": 100}, {"x": 251, "y": 97404, "w": 27, "h": 63, "m": 17, "t": 7}, {"x": 971, "y": 97450, "w": 26, "h": 323, "m": 36, "t": 26}, {"x": 3651, "y": 97476, "w": 27, "h": 61, "m": 107, "t": 97}, {"x": 1425, "y": 97483, "w": 27, "h": 311, "m": 48, "t": 38}, {"x": 2671, "y": 97584, "w": 26, "h": 193, "m": 81, "t": 71}, {"x": 2219, "y": 97587, "w": 26, "h": 203, "m": 69, "t": 59}, {"x": 3801, "y": 97605, "w": 27, "h": 62, "m": 111, "t": 101}, {"x": 212, "y": 97629, "w": 27, "h": 63, "m": 16, "t": 6}, {"x": 3612, "y": 97652, "w": 28, "h": 51, "m": 106, "t": 96}, {"x": 1763, "y": 97896, "w": 27, "h": 87, "m": 57, "t": 47}, {"x": 1952, "y": 97907, "w": 27, "h": 87, "m": 62, "t": 52}, {"x": 2067, "y": 97907, "w": 27, "h": 87, "m": 65, "t": 55}, {"x": 2859, "y": 97939, "w": 26, "h": 227, "m": 86, "t": 76}, {"x": 2406, "y": 97941, "w": 27, "h": 228, "m": 74, "t": 64}, {"x": 249, "y": 98166, "w": 28, "h": 52, "m": 17, "t": 7}, {"x": 3762, "y": 98195, "w": 28, "h": 50, "m": 110, "t": 100}, {"x": 892, "y": 98293, "w": 27, "h": 348, "m": 34, "t": 24}, {"x": 3649, "y": 98312, "w": 27, "h": 51, "m": 107, "t": 97}, {"x": 1348, "y": 98314, "w": 26, "h": 300, "m": 46, "t": 36}, {"x": 211, "y": 98345, "w": 27, "h": 50, "m": 16, "t": 6}, {"x": 2859, "y": 98376, "w": 27, "h": 534, "m": 86, "t": 76}, {"x": 2406, "y": 98378, "w": 27, "h": 535, "m": 74, "t": 64}, {"x": 3800, "y": 98382, "w": 27, "h": 63, "m": 111, "t": 101}, {"x": 3612, "y": 98489, "w": 27, "h": 52, "m": 106, "t": 96}, {"x": 1801, "y": 98749, "w": 27, "h": 144, "m": 58, "t": 48}, {"x": 1952, "y": 98760, "w": 27, "h": 144, "m": 62, "t": 52}, {"x": 2067, "y": 98760, "w": 27, "h": 143, "m": 65, "t": 55}, {"x": 2256, "y": 99122, "w": 27, "h": 86, "m": 70, "t": 60}, {"x": 2068, "y": 99123, "w": 27, "h": 98, "m": 65, "t": 55}, {"x": 1953, "y": 99124, "w": 27, "h": 110, "m": 62, "t": 52}, {"x": 3764, "y": 99280, "w": 27, "h": 75, "m": 110, "t": 100}, {"x": 3802, "y": 99471, "w": 26, "h": 61, "m": 111, "t": 101}, {"x": 2257, "y": 99479, "w": 27, "h": 408, "m": 70, "t": 60}, {"x": 2709, "y": 99488, "w": 27, "h": 385, "m": 82, "t": 72}, {"x": 252, "y": 99552, "w": 27, "h": 51, "m": 17, "t": 7}, {"x": 782, "y": 99704, "w": 26, "h": 290, "m": 31, "t": 21}, {"x": 3765, "y": 99732, "w": 27, "h": 63, "m": 110, "t": 100}, {"x": 3652, "y": 99745, "w": 27, "h": 64, "m": 107, "t": 97}, {"x": 1237, "y": 99784, "w": 26, "h": 254, "m": 43, "t": 33}, {"x": 214, "y": 99802, "w": 27, "h": 64, "m": 16, "t": 6}, {"x": 2861, "y": 99882, "w": 27, "h": 145, "m": 86, "t": 76}, {"x": 2409, "y": 99885, "w": 27, "h": 145, "m": 74, "t": 64}, {"x": 3802, "y": 99888, "w": 27, "h": 51, "m": 111, "t": 101}, {"x": 3614, "y": 99913, "w": 27, "h": 51, "m": 106, "t": 96}, {"x": 3765, "y": 100183, "w": 27, "h": 51, "m": 110, "t": 100}, {"x": 3803, "y": 100312, "w": 27, "h": 62, "m": 111, "t": 101}, {"x": 1955, "y": 100313, "w": 27, "h": 98, "m": 62, "t": 52}, {"x": 2070, "y": 100313, "w": 27, "h": 97, "m": 65, "t": 55}, {"x": 1804, "y": 100314, "w": 27, "h": 86, "m": 58, "t": 48}, {"x": 2976, "y": 100317, "w": 27, "h": 156, "m": 89, "t": 79}, {"x": 2523, "y": 100320, "w": 27, "h": 146, "m": 77, "t": 67}, {"x": 253, "y": 100586, "w": 28, "h": 50, "m": 17, "t": 7}, {"x": 3767, "y": 100678, "w": 27, "h": 62, "m": 110, "t": 100}, {"x": 708, "y": 100734, "w": 27, "h": 381, "m": 29, "t": 19}, {"x": 1163, "y": 100790, "w": 27, "h": 322, "m": 41, "t": 31}, {"x": 3654, "y": 100797, "w": 27, "h": 74, "m": 107, "t": 97}, {"x": 216, "y": 100820, "w": 27, "h": 74, "m": 16, "t": 6}, {"x": 2675, "y": 100862, "w": 26, "h": 3393, "m": 81, "t": 71}, {"x": 3804, "y": 100867, "w": 27, "h": 62, "m": 111, "t": 101}, {"x": 3128, "y": 100871, "w": 27, "h": 4286, "m": 93, "t": 83}, {"x": 3617, "y": 100962, "w": 27, "h": 63, "m": 106, "t": 96}, {"x": 1618, "y": 101236, "w": 26, "h": 98, "m": 53, "t": 43}, {"x": 1429, "y": 101248, "w": 27, "h": 86, "m": 48, "t": 38}, {"x": 1768, "y": 101259, "w": 27, "h": 96, "m": 57, "t": 47}, {"x": 1618, "y": 101566, "w": 27, "h": 112, "m": 53, "t": 43}, {"x": 1769, "y": 101577, "w": 26, "h": 98, "m": 57, "t": 47}, {"x": 1882, "y": 101612, "w": 27, "h": 98, "m": 60, "t": 50}, {"x": 1770, "y": 101923, "w": 27, "h": 85, "m": 57, "t": 47}, {"x": 1883, "y": 101933, "w": 26, "h": 99, "m": 60, "t": 50}, {"x": 2074, "y": 101955, "w": 26, "h": 110, "m": 65, "t": 55}, {"x": 2074, "y": 102228, "w": 27, "h": 86, "m": 65, "t": 55}, {"x": 1884, "y": 102229, "w": 26, "h": 86, "m": 60, "t": 50}, {"x": 2226, "y": 102308, "w": 26, "h": 75, "m": 69, "t": 59}, {"x": 2076, "y": 102604, "w": 27, "h": 97, "m": 65, "t": 55}, {"x": 2227, "y": 102639, "w": 26, "h": 71, "m": 69, "t": 59}, {"x": 2339, "y": 102661, "w": 27, "h": 85, "m": 72, "t": 62}, {"x": 2227, "y": 102955, "w": 27, "h": 228, "m": 69, "t": 59}, {"x": 2339, "y": 102966, "w": 27, "h": 204, "m": 72, "t": 62}, {"x": 2528, "y": 103035, "w": 27, "h": 180, "m": 77, "t": 67}, {"x": 1621, "y": 103637, "w": 27, "h": 167, "m": 53, "t": 43}, {"x": 1772, "y": 103694, "w": 27, "h": 131, "m": 57, "t": 47}, {"x": 1885, "y": 103705, "w": 27, "h": 142, "m": 60, "t": 50}, {"x": 2076, "y": 103796, "w": 26, "h": 121, "m": 65, "t": 55}, {"x": 2982, "y": 103799, "w": 27, "h": 842, "m": 89, "t": 79}, {"x": 2793, "y": 103813, "w": 27, "h": 640, "m": 84, "t": 74}, {"x": 1622, "y": 104400, "w": 27, "h": 192, "m": 53, "t": 43}, {"x": 1773, "y": 104470, "w": 26, "h": 144, "m": 57, "t": 47}, {"x": 1886, "y": 104503, "w": 27, "h": 157, "m": 60, "t": 50}, {"x": 2077, "y": 104596, "w": 27, "h": 121, "m": 65, "t": 55}, {"x": 1622, "y": 105250, "w": 27, "h": 192, "m": 53, "t": 43}, {"x": 1773, "y": 105319, "w": 26, "h": 158, "m": 57, "t": 47}, {"x": 1886, "y": 105400, "w": 27, "h": 147, "m": 60, "t": 50}, {"x": 2077, "y": 105496, "w": 26, "h": 121, "m": 65, "t": 55}, {"x": 3659, "y": 106774, "w": 26, "h": 62, "m": 107, "t": 97}, {"x": 3545, "y": 109083, "w": 27, "h": 582, "m": 104, "t": 94}]}